fpga2/src/biphasemark_decode.sv
`timescale 1ns / 1ps
`default_nettype none

module biphasemark_decode (input wire clk,
                input wire rst,
                input wire vin,
                input wire din,

                output logic dout,
                output logic vout,
                output logic [7:0] frame_counter,
                output logic channel
);

    // we wait for *any* preamble
    logic [7:0] preamble_counter;
    logic has_preamble_ended;
    logic [7:0] preamble_buffer;

    // we wait two clock cycles of data and immediately send the decoded bit
    logic [1:0] bmc_buffer;
    logic bmc_counter; 
    logic [6:0] data_counter; //This should count up to 56 to signify the end of a subframe and to disallow us sednding any preamble bits as data bits 

    // set of preambles
    typedef enum bit [7:0] {START0 = 8'b11101000, START1 = 8'b00010111, LEFT0 = 8'b11100010, LEFT1 = 8'b00011101,
    RIGHT0 = 8'b11100100, RIGHT1 = 8'b00011011} preamble_state;  
    preamble_state preamblestate; 

    always_ff@(posedge clk) begin
        if (rst) begin
            frame_counter <= 0;
            has_preamble_ended <= 0;
            preamble_counter <= 0;
            bmc_buffer <= 0;
            channel <= 0;
            bmc_counter <= 0;
            data_counter <= 0;
            vout <= 0;   
        end else begin
            if (!has_preamble_ended && vin) begin  // If we are reading the preamble
                    preamble_buffer <= {preamble_buffer[6:0], din};
                    data_counter <= 0; 
                    vout <= 0; 
                    bmc_counter <= 0; 
                    if ({preamble_buffer[6:0], din} == START0 || {preamble_buffer[6:0], din} == START1) begin
                        has_preamble_ended <= 1;
                        frame_counter <= 0;
                        channel <= 0;
                    end
                    else if (({preamble_buffer[6:0], din} == LEFT0 || {preamble_buffer[6:0], din} == LEFT1)) begin
                        has_preamble_ended <= 1;
                        frame_counter <= frame_counter + 1;
                        channel <= 0;
                    end                      
                    else if ({preamble_buffer[6:0], din} == RIGHT0 || {preamble_buffer[6:0], din} == RIGHT1) begin
                        has_preamble_ended <= 1;    
                        channel <= 1;
                    end
            end 
            else if (has_preamble_ended) begin // If we want to send the decoded data
                data_counter <= data_counter + 1;  
                bmc_counter = ~bmc_counter;    // This is BMC counter  
                bmc_buffer <= {bmc_buffer[0], din}; 
                if (bmc_counter == 1) begin  // This is equivalent to BMC counter being equal to 1. However if vout is 1 then it is valid next. 
                    if (data_counter > 0) begin
                        vout <= 1; 
                        if (bmc_buffer[1] == bmc_buffer[0]) begin 
                            dout <= 1'b0;
                        end else if (bmc_buffer[1] != bmc_buffer[0]) begin 
                            dout <= 1'b1; 
                        end 
                    end
                end else if (bmc_counter == 0) begin 
                    vout <= 0; 
                    if (data_counter == 57) begin // We stop when we reach 1 cycle more
                        has_preamble_ended <= 0;  
                        preamble_buffer <= {6'bX, {bmc_buffer[0], din}};  // WE PAD WITH X's to make sure that the preambles are not confused (if we pad it with zeros, we could have LEFT1 found before actually getting START0, for example)
                    end 
                end                
            end
            else begin // if we have not received any valid in signal, we just reset everything to default
                data_counter <= 0; 
                vout <= 0; 
                bmc_counter <= 0; 
            end
        end
    end
endmodule

`default_nettype wire

fpga2/sim/biphasemark_decode_tb.sv
`default_nettype none
`timescale 1ns / 1ps

module biphasemark_decode_tb;
    logic clk;
    logic rst;
    logic vin;
    logic din;
    logic dout;
    logic vout;
    logic [7:0] frame_counter;
    logic channel;

    biphasemark_decode my_biphasemark_decode(.clk(clk), .rst(rst), .vin(vin), .din(din), .dout(dout), .vout(vout), .frame_counter(frame_counter), .channel(channel));

    logic [63:0] test1 = 64'hE8_FF_FFFFFFFFFF_FF;
    logic [63:0] test2 = 64'hE8_CC_AAAAAAAAAA_CC;          // standard message with A's as data

    logic [63:0] test3_channelZ = 64'hE8_CC_AAAAAAAAAA_CC;  // packets sending all F's in biphase-mark encoding
    logic [63:0] test3_channelA = 64'hE2_CC_AAAAAAAAAA_CC;  // packets sending all F's in biphase-mark encoding
    logic [63:0] test3_channelB = 64'hE4_CC_AAAAAAAAAA_CC;  // packets sending all F's in biphase-mark encoding

    always begin
        #10;
        clk = !clk;
    end

    initial begin
        $dumpfile("biphasemark_decode.vcd");
        $dumpvars(0, biphasemark_decode_tb);
        $display("Starting Sim");
        clk = 0;
        rst = 0;
        #20;
        rst = 1;
        #30;
        rst = 0;

        /* ---------------------------------------------------------------
        *  TEST 1: Check if stuff goes through the aux and properly switches
        *  states.
        *  ---------------------------------------------------------------
        */ 
        vin = 1;
        for (int i = 0; i < 64; i = i + 1) begin
            din = test1[63 - i];
            #20;
        end
        vin = 0;
        #400;

        /* ---------------------------------------------------------------
        *  TEST 2: Send a single subframe of BMC encoded data
        *  ---------------------------------------------------------------
        */ 
        vin = 1;
        for (int i = 0; i < 64; i = i + 1) begin
            din = test2[63 - i];
            #20;
        end
        vin = 0;
        #400;

        /* ---------------------------------------------------------------
        *  TEST 3: Send an entire 192 blocks continuously
        *  ---------------------------------------------------------------
        */ 
        vin = 1;
        for (int i = 0; i < 384; i = i + 1) begin
            if (i == 0) begin
                for (int j = 0; j < 64; j = j + 1) begin
                    din = test3_channelZ[63 - j];
                    #20;
                end
            end else if (i % 2 == 0) begin
                for (int j = 0; j < 64; j = j + 1) begin
                    din = test3_channelA[63 - j];
                    #20;
                end
            end else if (i % 2 == 1) begin
                for (int j = 0; j < 64; j = j + 1) begin
                    din = test3_channelB[63 - j];
                    #20;
                end
            end
        end
        vin = 0;
        #400;

        /* ---------------------------------------------------------------
        *  TEST 4: Send two entire 192 blocks continuously
        *  ---------------------------------------------------------------
        */ 
        vin = 1;
        for (int i = 0; i < 384; i = i + 1) begin
            if (i == 0) begin
                for (int j = 0; j < 64; j = j + 1) begin
                    din = test3_channelZ[63 - j];
                    #20;
                end
            end else if (i % 2 == 0) begin
                for (int j = 0; j < 64; j = j + 1) begin
                    din = test3_channelA[63 - j];
                    #20;
                end
            end else if (i % 2 == 1) begin
                for (int j = 0; j < 64; j = j + 1) begin
                    din = test3_channelB[63 - j];
                    #20;
                end
            end
        end
        for (int i = 0; i < 384; i = i + 1) begin
            if (i == 0) begin
                for (int j = 0; j < 64; j = j + 1) begin
                    din = test3_channelZ[63 - j];
                    #20;
                end
            end else if (i % 2 == 0) begin
                for (int j = 0; j < 64; j = j + 1) begin
                    din = test3_channelA[63 - j];
                    #20;
                end
            end else if (i % 2 == 1) begin
                for (int j = 0; j < 64; j = j + 1) begin
                    din = test3_channelB[63 - j];
                    #20;
                end
            end
        end
        vin = 0;
        #400;

        /* ---------------------------------------------------------------
        *  TEST 5: Send data first, then trash (all 1s), then data again
        *  ---------------------------------------------------------------
        */ 
        vin = 1;
        for (int i = 0; i < 384; i = i + 1) begin
            if (i == 0) begin
                for (int j = 0; j < 64; j = j + 1) begin
                    din = test3_channelZ[63 - j];
                    #20;
                end
            end else if (i % 2 == 0) begin
                for (int j = 0; j < 64; j = j + 1) begin
                    din = test3_channelA[63 - j];
                    #20;
                end
            end else if (i % 2 == 1) begin
                for (int j = 0; j < 64; j = j + 1) begin
                    din = test3_channelB[63 - j];
                    #20;
                end
            end
        end
        vin = 0;
        for (int i = 0; i < 384; i = i + 1) begin
            din = 1;
            #20;
        end
        vin = 1;
        for (int i = 0; i < 384; i = i + 1) begin
            if (i == 0) begin
                for (int j = 0; j < 64; j = j + 1) begin
                    din = test3_channelZ[63 - j];
                    #20;
                end
            end else if (i % 2 == 0) begin
                for (int j = 0; j < 64; j = j + 1) begin
                    din = test3_channelA[63 - j];
                    #20;
                end
            end else if (i % 2 == 1) begin
                for (int j = 0; j < 64; j = j + 1) begin
                    din = test3_channelB[63 - j];
                    #20;
                end
            end
        end
        vin = 0;
        #400;
        
        $display("Finishing Sim");
        $finish;
    end

endmodule

`default_nettype wire

fpga2/biphasemark_decode.vcd
$date
	Wed Dec 07 19:26:48 2022
$end
$version
	Icarus Verilog
$end
$timescale
	1ps
$end
$scope module biphasemark_decode_tb $end
$var wire 1 ! vout $end
$var wire 8 " frame_counter [7:0] $end
$var wire 1 # dout $end
$var wire 1 $ channel $end
$var reg 1 % clk $end
$var reg 1 & din $end
$var reg 1 ' rst $end
$var reg 64 ( test1 [63:0] $end
$var reg 64 ) test2 [63:0] $end
$var reg 64 * test3_channelA [63:0] $end
$var reg 64 + test3_channelB [63:0] $end
$var reg 64 , test3_channelZ [63:0] $end
$var reg 1 - vin $end
$scope module my_biphasemark_decode $end
$var wire 1 % clk $end
$var wire 1 & din $end
$var wire 1 ' rst $end
$var wire 1 - vin $end
$var reg 2 . bmc_buffer [1:0] $end
$var reg 1 / bmc_counter $end
$var reg 1 $ channel $end
$var reg 7 0 data_counter [6:0] $end
$var reg 1 # dout $end
$var reg 8 1 frame_counter [7:0] $end
$var reg 1 2 has_preamble_ended $end
$var reg 8 3 preamble_buffer [7:0] $end
$var reg 8 4 preamble_counter [7:0] $end
$var reg 1 ! vout $end
$upscope $end
$scope begin $ivl_for_loop0 $end
$var integer 32 5 i [31:0] $end
$scope begin $ivl_for_loop1 $end
$var integer 32 6 j [31:0] $end
$upscope $end
$scope begin $ivl_for_loop2 $end
$var integer 32 7 j [31:0] $end
$upscope $end
$scope begin $ivl_for_loop3 $end
$var integer 32 8 j [31:0] $end
$upscope $end
$upscope $end
$scope begin $ivl_for_loop4 $end
$var integer 32 9 i [31:0] $end
$upscope $end
$scope begin $ivl_for_loop5 $end
$var integer 32 : i [31:0] $end
$scope begin $ivl_for_loop6 $end
$var integer 32 ; j [31:0] $end
$upscope $end
$scope begin $ivl_for_loop7 $end
$var integer 32 < j [31:0] $end
$upscope $end
$scope begin $ivl_for_loop8 $end
$var integer 32 = j [31:0] $end
$upscope $end
$upscope $end
$upscope $end
$enddefinitions $end
$comment Show the parameter values. $end
$dumpall
$end
#0
$dumpvars
b0 =
b0 <
b0 ;
b0 :
b0 9
b0 8
b0 7
b0 6
b0 5
bx 4
bx 3
x2
bx 1
bx 0
x/
bx .
x-
b1110100011001100101010101010101010101010101010101010101011001100 ,
b1110010011001100101010101010101010101010101010101010101011001100 +
b1110001011001100101010101010101010101010101010101010101011001100 *
b1110100011001100101010101010101010101010101010101010101011001100 )
b1110100011111111111111111111111111111111111111111111111111111111 (
0'
x&
0%
x$
x#
bx "
x!
$end
#10000
0/
0!
b0 0
1%
#20000
0%
1'
#30000
0$
b0 .
b0 4
02
b0 "
b0 1
1%
#40000
0%
#50000
bx1 3
1%
1&
1-
0'
#60000
0%
#70000
bx11 3
1%
b1 6
#80000
0%
#90000
bx111 3
1%
b10 6
#100000
0%
#110000
bx1110 3
1%
0&
b11 6
#120000
0%
#130000
bx11101 3
1%
1&
b100 6
#140000
0%
#150000
bx111010 3
1%
0&
b101 6
#160000
0%
#170000
bx1110100 3
1%
b110 6
#180000
0%
#190000
12
b11101000 3
1%
b111 6
#200000
0%
#210000
b1 .
b1 0
1/
1%
1&
b1000 6
#220000
0%
#230000
b11 .
b10 0
0/
1%
b1001 6
#240000
0%
#250000
0#
1!
b10 .
b11 0
1/
1%
0&
b1010 6
#260000
0%
#270000
0!
b0 .
b100 0
0/
1%
b1011 6
#280000
0%
#290000
1!
b1 .
b101 0
1/
1%
1&
b1100 6
#300000
0%
#310000
0!
b11 .
b110 0
0/
1%
b1101 6
#320000
0%
#330000
1!
b10 .
b111 0
1/
1%
0&
b1110 6
#340000
0%
#350000
0!
b0 .
b1000 0
0/
1%
b1111 6
#360000
0%
#370000
1!
b1 .
b1001 0
1/
1%
1&
b10000 6
#380000
0%
#390000
0!
b10 .
b1010 0
0/
1%
0&
b10001 6
#400000
0%
#410000
1#
1!
b1 .
b1011 0
1/
1%
1&
b10010 6
#420000
0%
#430000
0!
b10 .
b1100 0
0/
1%
0&
b10011 6
#440000
0%
#450000
1!
b1 .
b1101 0
1/
1%
1&
b10100 6
#460000
0%
#470000
0!
b10 .
b1110 0
0/
1%
0&
b10101 6
#480000
0%
#490000
1!
b1 .
b1111 0
1/
1%
1&
b10110 6
#500000
0%
#510000
0!
b10 .
b10000 0
0/
1%
0&
b10111 6
#520000
0%
#530000
1!
b1 .
b10001 0
1/
1%
1&
b11000 6
#540000
0%
#550000
0!
b10 .
b10010 0
0/
1%
0&
b11001 6
#560000
0%
#570000
1!
b1 .
b10011 0
1/
1%
1&
b11010 6
#580000
0%
#590000
0!
b10 .
b10100 0
0/
1%
0&
b11011 6
#600000
0%
#610000
1!
b1 .
b10101 0
1/
1%
1&
b11100 6
#620000
0%
#630000
0!
b10 .
b10110 0
0/
1%
0&
b11101 6
#640000
0%
#650000
1!
b1 .
b10111 0
1/
1%
1&
b11110 6
#660000
0%
#670000
0!
b10 .
b11000 0
0/
1%
0&
b11111 6
#680000
0%
#690000
1!
b1 .
b11001 0
1/
1%
1&
b100000 6
#700000
0%
#710000
0!
b10 .
b11010 0
0/
1%
0&
b100001 6
#720000
0%
#730000
1!
b1 .
b11011 0
1/
1%
1&
b100010 6
#740000
0%
#750000
0!
b10 .
b11100 0
0/
1%
0&
b100011 6
#760000
0%
#770000
1!
b1 .
b11101 0
1/
1%
1&
b100100 6
#780000
0%
#790000
0!
b10 .
b11110 0
0/
1%
0&
b100101 6
#800000
0%
#810000
1!
b1 .
b11111 0
1/
1%
1&
b100110 6
#820000
0%
#830000
0!
b10 .
b100000 0
0/
1%
0&
b100111 6
#840000
0%
#850000
1!
b1 .
b100001 0
1/
1%
1&
b101000 6
#860000
0%
#870000
0!
b10 .
b100010 0
0/
1%
0&
b101001 6
#880000
0%
#890000
1!
b1 .
b100011 0
1/
1%
1&
b101010 6
#900000
0%
#910000
0!
b10 .
b100100 0
0/
1%
0&
b101011 6
#920000
0%
#930000
1!
b1 .
b100101 0
1/
1%
1&
b101100 6
#940000
0%
#950000
0!
b10 .
b100110 0
0/
1%
0&
b101101 6
#960000
0%
#970000
1!
b1 .
b100111 0
1/
1%
1&
b101110 6
#980000
0%
#990000
0!
b10 .
b101000 0
0/
1%
0&
b101111 6
#1000000
0%
#1010000
1!
b1 .
b101001 0
1/
1%
1&
b110000 6
#1020000
0%
#1030000
0!
b10 .
b101010 0
0/
1%
0&
b110001 6
#1040000
0%
#1050000
1!
b1 .
b101011 0
1/
1%
1&
b110010 6
#1060000
0%
#1070000
0!
b10 .
b101100 0
0/
1%
0&
b110011 6
#1080000
0%
#1090000
1!
b1 .
b101101 0
1/
1%
1&
b110100 6
#1100000
0%
#1110000
0!
b10 .
b101110 0
0/
1%
0&
b110101 6
#1120000
0%
#1130000
1!
b1 .
b101111 0
1/
1%
1&
b110110 6
#1140000
0%
#1150000
0!
b10 .
b110000 0
0/
1%
0&
b110111 6
#1160000
0%
#1170000
1!
b1 .
b110001 0
1/
1%
1&
b111000 6
#1180000
0%
#1190000
0!
b11 .
b110010 0
0/
1%
b111001 6
#1200000
0%
#1210000
0#
1!
b10 .
b110011 0
1/
1%
0&
b111010 6
#1220000
0%
#1230000
0!
b0 .
b110100 0
0/
1%
b111011 6
#1240000
0%
#1250000
1!
b1 .
b110101 0
1/
1%
1&
b111100 6
#1260000
0%
#1270000
0!
b11 .
b110110 0
0/
1%
b111101 6
#1280000
0%
#1290000
1!
b10 .
b110111 0
1/
1%
0&
b111110 6
#1300000
0%
#1310000
0!
b0 .
b111000 0
0/
1%
b111111 6
#1320000
0%
#1330000
1!
b1 .
b111001 0
1/
1%
1&
b1 5
b1000000 6
#1340000
0%
#1350000
bx11 3
02
0!
b11 .
b111010 0
0/
1%
b1 8
#1360000
0%
#1370000
b0 0
bx111 3
1%
b10 8
#1380000
0%
#1390000
bx1110 3
1%
0&
b11 8
#1400000
0%
#1410000
bx11100 3
1%
b100 8
#1420000
0%
#1430000
bx111001 3
1%
1&
b101 8
#1440000
0%
#1450000
bx1110010 3
1%
0&
b110 8
#1460000
0%
#1470000
1$
12
b11100100 3
1%
b111 8
#1480000
0%
#1490000
b1 0
1/
1%
1&
b1000 8
#1500000
0%
#1510000
b10 0
0/
1%
b1001 8
#1520000
0%
#1530000
1!
b10 .
b11 0
1/
1%
0&
b1010 8
#1540000
0%
#1550000
0!
b0 .
b100 0
0/
1%
b1011 8
#1560000
0%
#1570000
1!
b1 .
b101 0
1/
1%
1&
b1100 8
#1580000
0%
#1590000
0!
b11 .
b110 0
0/
1%
b1101 8
#1600000
0%
#1610000
1!
b10 .
b111 0
1/
1%
0&
b1110 8
#1620000
0%
#1630000
0!
b0 .
b1000 0
0/
1%
b1111 8
#1640000
0%
#1650000
1!
b1 .
b1001 0
1/
1%
1&
b10000 8
#1660000
0%
#1670000
0!
b10 .
b1010 0
0/
1%
0&
b10001 8
#1680000
0%
#1690000
1#
1!
b1 .
b1011 0
1/
1%
1&
b10010 8
#1700000
0%
#1710000
0!
b10 .
b1100 0
0/
1%
0&
b10011 8
#1720000
0%
#1730000
1!
b1 .
b1101 0
1/
1%
1&
b10100 8
#1740000
0%
#1750000
0!
b10 .
b1110 0
0/
1%
0&
b10101 8
#1760000
0%
#1770000
1!
b1 .
b1111 0
1/
1%
1&
b10110 8
#1780000
0%
#1790000
0!
b10 .
b10000 0
0/
1%
0&
b10111 8
#1800000
0%
#1810000
1!
b1 .
b10001 0
1/
1%
1&
b11000 8
#1820000
0%
#1830000
0!
b10 .
b10010 0
0/
1%
0&
b11001 8
#1840000
0%
#1850000
1!
b1 .
b10011 0
1/
1%
1&
b11010 8
#1860000
0%
#1870000
0!
b10 .
b10100 0
0/
1%
0&
b11011 8
#1880000
0%
#1890000
1!
b1 .
b10101 0
1/
1%
1&
b11100 8
#1900000
0%
#1910000
0!
b10 .
b10110 0
0/
1%
0&
b11101 8
#1920000
0%
#1930000
1!
b1 .
b10111 0
1/
1%
1&
b11110 8
#1940000
0%
#1950000
0!
b10 .
b11000 0
0/
1%
0&
b11111 8
#1960000
0%
#1970000
1!
b1 .
b11001 0
1/
1%
1&
b100000 8
#1980000
0%
#1990000
0!
b10 .
b11010 0
0/
1%
0&
b100001 8
#2000000
0%
#2010000
1!
b1 .
b11011 0
1/
1%
1&
b100010 8
#2020000
0%
#2030000
0!
b10 .
b11100 0
0/
1%
0&
b100011 8
#2040000
0%
#2050000
1!
b1 .
b11101 0
1/
1%
1&
b100100 8
#2060000
0%
#2070000
0!
b10 .
b11110 0
0/
1%
0&
b100101 8
#2080000
0%
#2090000
1!
b1 .
b11111 0
1/
1%
1&
b100110 8
#2100000
0%
#2110000
0!
b10 .
b100000 0
0/
1%
0&
b100111 8
#2120000
0%
#2130000
1!
b1 .
b100001 0
1/
1%
1&
b101000 8
#2140000
0%
#2150000
0!
b10 .
b100010 0
0/
1%
0&
b101001 8
#2160000
0%
#2170000
1!
b1 .
b100011 0
1/
1%
1&
b101010 8
#2180000
0%
#2190000
0!
b10 .
b100100 0
0/
1%
0&
b101011 8
#2200000
0%
#2210000
1!
b1 .
b100101 0
1/
1%
1&
b101100 8
#2220000
0%
#2230000
0!
b10 .
b100110 0
0/
1%
0&
b101101 8
#2240000
0%
#2250000
1!
b1 .
b100111 0
1/
1%
1&
b101110 8
#2260000
0%
#2270000
0!
b10 .
b101000 0
0/
1%
0&
b101111 8
#2280000
0%
#2290000
1!
b1 .
b101001 0
1/
1%
1&
b110000 8
#2300000
0%
#2310000
0!
b10 .
b101010 0
0/
1%
0&
b110001 8
#2320000
0%
#2330000
1!
b1 .
b101011 0
1/
1%
1&
b110010 8
#2340000
0%
#2350000
0!
b10 .
b101100 0
0/
1%
0&
b110011 8
#2360000
0%
#2370000
1!
b1 .
b101101 0
1/
1%
1&
b110100 8
#2380000
0%
#2390000
0!
b10 .
b101110 0
0/
1%
0&
b110101 8
#2400000
0%
#2410000
1!
b1 .
b101111 0
1/
1%
1&
b110110 8
#2420000
0%
#2430000
0!
b10 .
b110000 0
0/
1%
0&
b110111 8
#2440000
0%
#2450000
1!
b1 .
b110001 0
1/
1%
1&
b111000 8
#2460000
0%
#2470000
0!
b11 .
b110010 0
0/
1%
b111001 8
#2480000
0%
#2490000
0#
1!
b10 .
b110011 0
1/
1%
0&
b111010 8
#2500000
0%
#2510000
0!
b0 .
b110100 0
0/
1%
b111011 8
#2520000
0%
#2530000
1!
b1 .
b110101 0
1/
1%
1&
b111100 8
#2540000
0%
#2550000
0!
b11 .
b110110 0
0/
1%
b111101 8
#2560000
0%
#2570000
1!
b10 .
b110111 0
1/
1%
0&
b111110 8
#2580000
0%
#2590000
0!
b0 .
b111000 0
0/
1%
b111111 8
#2600000
0%
#2610000
1!
b1 .
b111001 0
1/
1%
1&
b10 5
b1000000 8
#2620000
0%
#2630000
bx11 3
02
0!
b11 .
b111010 0
0/
1%
b1 7
#2640000
0%
#2650000
b0 0
bx111 3
1%
b10 7
#2660000
0%
#2670000
bx1110 3
1%
0&
b11 7
#2680000
0%
#2690000
bx11100 3
1%
b100 7
#2700000
0%
#2710000
bx111000 3
1%
b101 7
#2720000
0%
#2730000
bx1110001 3
1%
1&
b110 7
#2740000
0%
#2750000
0$
b1 "
b1 1
12
b11100010 3
1%
0&
b111 7
#2760000
0%
#2770000
b1 0
1/
1%
1&
b1000 7
#2780000
0%
#2790000
b10 0
0/
1%
b1001 7
#2800000
0%
#2810000
1!
b10 .
b11 0
1/
1%
0&
b1010 7
#2820000
0%
#2830000
0!
b0 .
b100 0
0/
1%
b1011 7
#2840000
0%
#2850000
1!
b1 .
b101 0
1/
1%
1&
b1100 7
#2860000
0%
#2870000
0!
b11 .
b110 0
0/
1%
b1101 7
#2880000
0%
#2890000
1!
b10 .
b111 0
1/
1%
0&
b1110 7
#2900000
0%
#2910000
0!
b0 .
b1000 0
0/
1%
b1111 7
#2920000
0%
#2930000
1!
b1 .
b1001 0
1/
1%
1&
b10000 7
#2940000
0%
#2950000
0!
b10 .
b1010 0
0/
1%
0&
b10001 7
#2960000
0%
#2970000
1#
1!
b1 .
b1011 0
1/
1%
1&
b10010 7
#2980000
0%
#2990000
0!
b10 .
b1100 0
0/
1%
0&
b10011 7
#3000000
0%
#3010000
1!
b1 .
b1101 0
1/
1%
1&
b10100 7
#3020000
0%
#3030000
0!
b10 .
b1110 0
0/
1%
0&
b10101 7
#3040000
0%
#3050000
1!
b1 .
b1111 0
1/
1%
1&
b10110 7
#3060000
0%
#3070000
0!
b10 .
b10000 0
0/
1%
0&
b10111 7
#3080000
0%
#3090000
1!
b1 .
b10001 0
1/
1%
1&
b11000 7
#3100000
0%
#3110000
0!
b10 .
b10010 0
0/
1%
0&
b11001 7
#3120000
0%
#3130000
1!
b1 .
b10011 0
1/
1%
1&
b11010 7
#3140000
0%
#3150000
0!
b10 .
b10100 0
0/
1%
0&
b11011 7
#3160000
0%
#3170000
1!
b1 .
b10101 0
1/
1%
1&
b11100 7
#3180000
0%
#3190000
0!
b10 .
b10110 0
0/
1%
0&
b11101 7
#3200000
0%
#3210000
1!
b1 .
b10111 0
1/
1%
1&
b11110 7
#3220000
0%
#3230000
0!
b10 .
b11000 0
0/
1%
0&
b11111 7
#3240000
0%
#3250000
1!
b1 .
b11001 0
1/
1%
1&
b100000 7
#3260000
0%
#3270000
0!
b10 .
b11010 0
0/
1%
0&
b100001 7
#3280000
0%
#3290000
1!
b1 .
b11011 0
1/
1%
1&
b100010 7
#3300000
0%
#3310000
0!
b10 .
b11100 0
0/
1%
0&
b100011 7
#3320000
0%
#3330000
1!
b1 .
b11101 0
1/
1%
1&
b100100 7
#3340000
0%
#3350000
0!
b10 .
b11110 0
0/
1%
0&
b100101 7
#3360000
0%
#3370000
1!
b1 .
b11111 0
1/
1%
1&
b100110 7
#3380000
0%
#3390000
0!
b10 .
b100000 0
0/
1%
0&
b100111 7
#3400000
0%
#3410000
1!
b1 .
b100001 0
1/
1%
1&
b101000 7
#3420000
0%
#3430000
0!
b10 .
b100010 0
0/
1%
0&
b101001 7
#3440000
0%
#3450000
1!
b1 .
b100011 0
1/
1%
1&
b101010 7
#3460000
0%
#3470000
0!
b10 .
b100100 0
0/
1%
0&
b101011 7
#3480000
0%
#3490000
1!
b1 .
b100101 0
1/
1%
1&
b101100 7
#3500000
0%
#3510000
0!
b10 .
b100110 0
0/
1%
0&
b101101 7
#3520000
0%
#3530000
1!
b1 .
b100111 0
1/
1%
1&
b101110 7
#3540000
0%
#3550000
0!
b10 .
b101000 0
0/
1%
0&
b101111 7
#3560000
0%
#3570000
1!
b1 .
b101001 0
1/
1%
1&
b110000 7
#3580000
0%
#3590000
0!
b10 .
b101010 0
0/
1%
0&
b110001 7
#3600000
0%
#3610000
1!
b1 .
b101011 0
1/
1%
1&
b110010 7
#3620000
0%
#3630000
0!
b10 .
b101100 0
0/
1%
0&
b110011 7
#3640000
0%
#3650000
1!
b1 .
b101101 0
1/
1%
1&
b110100 7
#3660000
0%
#3670000
0!
b10 .
b101110 0
0/
1%
0&
b110101 7
#3680000
0%
#3690000
1!
b1 .
b101111 0
1/
1%
1&
b110110 7
#3700000
0%
#3710000
0!
b10 .
b110000 0
0/
1%
0&
b110111 7
#3720000
0%
#3730000
1!
b1 .
b110001 0
1/
1%
1&
b111000 7
#3740000
0%
#3750000
0!
b11 .
b110010 0
0/
1%
b111001 7
#3760000
0%
#3770000
0#
1!
b10 .
b110011 0
1/
1%
0&
b111010 7
#3780000
0%
#3790000
0!
b0 .
b110100 0
0/
1%
b111011 7
#3800000
0%
#3810000
1!
b1 .
b110101 0
1/
1%
1&
b111100 7
#3820000
0%
#3830000
0!
b11 .
b110110 0
0/
1%
b111101 7
#3840000
0%
#3850000
1!
b10 .
b110111 0
1/
1%
0&
b111110 7
#3860000
0%
#3870000
0!
b0 .
b111000 0
0/
1%
b111111 7
#3880000
0%
#3890000
1!
b1 .
b111001 0
1/
1%
1&
b0 8
b11 5
b1000000 7
#3900000
0%
#3910000
bx11 3
02
0!
b11 .
b111010 0
0/
1%
b1 8
#3920000
0%
#3930000
b0 0
bx111 3
1%
b10 8
#3940000
0%
#3950000
bx1110 3
1%
0&
b11 8
#3960000
0%
#3970000
bx11100 3
1%
b100 8
#3980000
0%
#3990000
bx111001 3
1%
1&
b101 8
#4000000
0%
#4010000
bx1110010 3
1%
0&
b110 8
#4020000
0%
#4030000
1$
12
b11100100 3
1%
b111 8
#4040000
0%
#4050000
b1 0
1/
1%
1&
b1000 8
#4060000
0%
#4070000
b10 0
0/
1%
b1001 8
#4080000
0%
#4090000
1!
b10 .
b11 0
1/
1%
0&
b1010 8
#4100000
0%
#4110000
0!
b0 .
b100 0
0/
1%
b1011 8
#4120000
0%
#4130000
1!
b1 .
b101 0
1/
1%
1&
b1100 8
#4140000
0%
#4150000
0!
b11 .
b110 0
0/
1%
b1101 8
#4160000
0%
#4170000
1!
b10 .
b111 0
1/
1%
0&
b1110 8
#4180000
0%
#4190000
0!
b0 .
b1000 0
0/
1%
b1111 8
#4200000
0%
#4210000
1!
b1 .
b1001 0
1/
1%
1&
b10000 8
#4220000
0%
#4230000
0!
b10 .
b1010 0
0/
1%
0&
b10001 8
#4240000
0%
#4250000
1#
1!
b1 .
b1011 0
1/
1%
1&
b10010 8
#4260000
0%
#4270000
0!
b10 .
b1100 0
0/
1%
0&
b10011 8
#4280000
0%
#4290000
1!
b1 .
b1101 0
1/
1%
1&
b10100 8
#4300000
0%
#4310000
0!
b10 .
b1110 0
0/
1%
0&
b10101 8
#4320000
0%
#4330000
1!
b1 .
b1111 0
1/
1%
1&
b10110 8
#4340000
0%
#4350000
0!
b10 .
b10000 0
0/
1%
0&
b10111 8
#4360000
0%
#4370000
1!
b1 .
b10001 0
1/
1%
1&
b11000 8
#4380000
0%
#4390000
0!
b10 .
b10010 0
0/
1%
0&
b11001 8
#4400000
0%
#4410000
1!
b1 .
b10011 0
1/
1%
1&
b11010 8
#4420000
0%
#4430000
0!
b10 .
b10100 0
0/
1%
0&
b11011 8
#4440000
0%
#4450000
1!
b1 .
b10101 0
1/
1%
1&
b11100 8
#4460000
0%
#4470000
0!
b10 .
b10110 0
0/
1%
0&
b11101 8
#4480000
0%
#4490000
1!
b1 .
b10111 0
1/
1%
1&
b11110 8
#4500000
0%
#4510000
0!
b10 .
b11000 0
0/
1%
0&
b11111 8
#4520000
0%
#4530000
1!
b1 .
b11001 0
1/
1%
1&
b100000 8
#4540000
0%
#4550000
0!
b10 .
b11010 0
0/
1%
0&
b100001 8
#4560000
0%
#4570000
1!
b1 .
b11011 0
1/
1%
1&
b100010 8
#4580000
0%
#4590000
0!
b10 .
b11100 0
0/
1%
0&
b100011 8
#4600000
0%
#4610000
1!
b1 .
b11101 0
1/
1%
1&
b100100 8
#4620000
0%
#4630000
0!
b10 .
b11110 0
0/
1%
0&
b100101 8
#4640000
0%
#4650000
1!
b1 .
b11111 0
1/
1%
1&
b100110 8
#4660000
0%
#4670000
0!
b10 .
b100000 0
0/
1%
0&
b100111 8
#4680000
0%
#4690000
1!
b1 .
b100001 0
1/
1%
1&
b101000 8
#4700000
0%
#4710000
0!
b10 .
b100010 0
0/
1%
0&
b101001 8
#4720000
0%
#4730000
1!
b1 .
b100011 0
1/
1%
1&
b101010 8
#4740000
0%
#4750000
0!
b10 .
b100100 0
0/
1%
0&
b101011 8
#4760000
0%
#4770000
1!
b1 .
b100101 0
1/
1%
1&
b101100 8
#4780000
0%
#4790000
0!
b10 .
b100110 0
0/
1%
0&
b101101 8
#4800000
0%
#4810000
1!
b1 .
b100111 0
1/
1%
1&
b101110 8
#4820000
0%
#4830000
0!
b10 .
b101000 0
0/
1%
0&
b101111 8
#4840000
0%
#4850000
1!
b1 .
b101001 0
1/
1%
1&
b110000 8
#4860000
0%
#4870000
0!
b10 .
b101010 0
0/
1%
0&
b110001 8
#4880000
0%
#4890000
1!
b1 .
b101011 0
1/
1%
1&
b110010 8
#4900000
0%
#4910000
0!
b10 .
b101100 0
0/
1%
0&
b110011 8
#4920000
0%
#4930000
1!
b1 .
b101101 0
1/
1%
1&
b110100 8
#4940000
0%
#4950000
0!
b10 .
b101110 0
0/
1%
0&
b110101 8
#4960000
0%
#4970000
1!
b1 .
b101111 0
1/
1%
1&
b110110 8
