fpga2/src/crc_calc.sv
`default_nettype none
`timescale 1ns / 1ps

module crc_calc #(
  parameter bit [63 : 0] POLY       = 16'h8005,
  parameter int          CRC_SIZE   = 16,
  parameter int          DATA_WIDTH = 8,
  parameter bit [63 : 0] INIT       = 16'h0000,
  parameter int          REF_IN     = 1,
  parameter int          REF_OUT    = 1,
  parameter bit [63 : 0] XOR_OUT    = 16'hffff
)(
  input wire                      clk_i,
  input wire                      rst_i,
  input wire                      soft_reset_i,
  input wire                      valid_i,
  input wire [DATA_WIDTH - 1 : 0] data_i,
  output logic [CRC_SIZE - 1 : 0]   crc_o
);

/*
* Imported CRC module that allows for checking of the CRC for arbitrarily large input values
* and arbitrary polynomials. 
*/

logic [CRC_SIZE - 1 : 0] crc;
logic [CRC_SIZE - 1 : 0] crc_next;
logic [CRC_SIZE - 1 : 0] crc_prev;

always_ff @( posedge clk_i )
  if( rst_i )
    crc <= INIT[CRC_SIZE - 1 : 0];
  else
    if( soft_reset_i )
      crc <= INIT[CRC_SIZE - 1 : 0];
    else
      if( valid_i )
        crc <= crc_next;

assign crc_o = crc ^ XOR_OUT[CRC_SIZE - 1 : 0];

generate
  if( REF_OUT )
    if( REF_IN )
      begin : ref_out_ref_in
        always@(*)
          begin
            crc_next = crc;
            crc_prev = crc;
            for( int i = 0 ; i < DATA_WIDTH; i++ )
              begin
                crc_next[CRC_SIZE - 1] = crc_prev[0] ^ data_i[i];
                for( int j = 1; j < CRC_SIZE; j++ )
                  if( POLY[j] )
                    crc_next[CRC_SIZE - 1 - j] = crc_prev[CRC_SIZE - j] ^ crc_prev[0] ^ data_i[i];
                  else
                    crc_next[CRC_SIZE - 1 - j] = crc_prev[CRC_SIZE - j]; 
                 crc_prev = crc_next;
              end
          end
      end
    else
      begin : ref_out_n_ref_in
        always@(*)
          begin
            crc_next = crc;
            crc_prev = crc;
            for( int i = 0; i < DATA_WIDTH; i++ )
              begin
                crc_next[0] = crc_prev[CRC_SIZE - 1] ^ data_i[i];
                for( int j = 1; j < CRC_SIZE; j++ )
                  if( POLY[j] )
                    crc_next[j] = crc_prev[j - 1] ^ crc_prev[CRC_SIZE - 1] ^ data_i[i];
                  else
                    crc_next[j] = crc_prev[j - 1];
                crc_prev = crc_next;
              end
          end
      end
  else
    if( REF_IN )
      begin : n_ref_out_ref_in
        always@(*)
          begin
            crc_next = crc;
            crc_prev = crc;
            for( int i = 0; i < DATA_WIDTH; i ++ )
              begin
                crc_next[CRC_SIZE - 1] = crc_prev[0] ^ data_i[ DATA_WIDTH - 1 - i];
                for( int j = 1; j < CRC_SIZE; j++ )
                  if( POLY[j] )
                    crc_next[CRC_SIZE - 1 - j] = crc_prev[CRC_SIZE - j] ^ crc_prev[0] ^ data_i[DATA_WIDTH - 1 - i];
                  else
                    crc_next[CRC_SIZE - 1 - j] = crc_prev[CRC_SIZE - j];
                crc_prev = crc_next;
              end
          end
      end
    else
      begin : n_ref_out_n_ref_in
        always@(*)
          begin
            crc_next = crc;
            crc_prev = crc;
            for( int i = 0; i < DATA_WIDTH; i ++ )
              begin
                crc_next[0] = crc_prev[CRC_SIZE - 1] ^ data_i[DATA_WIDTH - 1 - i];
                for( int j = 1; j < CRC_SIZE; j++ )
                  if( POLY[j] )
                    crc_next[j] = crc_prev[j - 1] ^ crc_prev[CRC_SIZE - 1] ^ data_i[DATA_WIDTH - 1 - i];
                  else
                    crc_next[j] = crc_prev[j - 1];
                crc_prev = crc_next;
              end
          end
      end
endgenerate

endmodule

`default_nettype wire

fpga2/sim/crcc_tb.sv
`default_nettype none
`timescale 1ns / 1ps

module crcc_tb;
    logic clk;
    logic rst;
    logic axiiv;
    logic [7:0] axiid;
    logic [7:0] axiid_alt;
    logic axiov;
    logic [7:0] axiod;
    logic soft_reset_i;

    // crcc my_crcc(.clk(clk), .rst(rst), .axiiv(axiiv), .axiid(axiid), .axiov(axiov), .axiod(axiod));

    crc_calc #(.POLY(8'h1D), .CRC_SIZE(8), .DATA_WIDTH(8), .INIT(8'hFF), .REF_IN(1), .REF_OUT(1), .XOR_OUT(8'h0)) my_crc_calc(.clk_i(clk), .rst_i(rst), .soft_reset_i(soft_reset_i), .valid_i(axiiv), .data_i(axiid), .crc_o(axiod));

    logic [15:0] test1 = 16'hFFFF;
    logic [31:0] test2 = 32'h12AB34CD;
    logic [71:0] test3 = 72'h313233343536373839;
    logic [183:0] test5 = 184'hA129BB293000021399BFF930EEBA99222019823749CDD1;

    always begin
        #10;
        clk = !clk;
    end

    /* ---------------------------------------------------------------
     *  IMPORTANT NOTE:  
     *     THE INPUTS FOR THE CRC-8 HAVE TO BE BYTE-REVERSED
     *     IT IS SOMETHING TO TAKE INTO ACCOUNT WHEN VERIFYING THE CRC-8 TOO
     * ---------------------------------------------------------------
    */ 

    initial begin
        $dumpfile("crcc.vcd");
        $dumpvars(0, crcc_tb);
        $display("Starting Sim");
        clk = 0;
        rst = 0;
        #20;
        rst = 1;
        #30;
        rst = 0;

        /*
        TEST 1: Input: 0xFFFF, Expected Output: 0x23
        */
        // axiiv = 1'b1;
        // for (int i = 15; i >= 0; i = i - 8) begin
        //     axiid = test1[i -: 8];
        //     #20;
        // end
        // axiiv = 1'b0;
        // if (axiod == 8'h23) begin
        //     $display("TEST 1 PASSED");
        // end else begin 
        //     $display("TEST 1 FAILED");
        //     $display("%h", axiod);
        // end
        // $display("---------------------------");
        // #20;
        // rst = 1;
        // #20;

        /*
        TEST 2: Input: 0xCD, Expected Output: 0xF1
        */
        // rst = 0;
        // axiiv = 1'b1;
        // for (int i = 7; i >= 0; i = i - 8) begin
        //     axiid = test2[i -: 8];
        //     #20;
        // end
        // axiiv = 1'b0;
        // if (axiod == 8'hF1) begin
        //     $display("TEST 2 PASSED");
        // end else begin 
        //     $display("TEST 2 FAILED");
        // end
        // $display("---------------------------");
        // #20;
        // rst = 1;
        // #20;

        /*
        TEST 3: Input: 0x12AB34CD, Expected Output: 0x6B
        */
        // rst = 0;
        // axiiv = 1'b1;
        // for (int i = 31; i >= 0; i = i - 8) begin
        //     axiid = test2[i -: 8];
        //     #20;
        // end
        // axiiv = 1'b0;
        // if (axiod == 8'h6B) begin
        //     $display("TEST 3 PASSED");
        // end else begin 
        //     $display("TEST 3 FAILED");
        // end
        // $display("---------------------------");
        // #20;
        // rst = 1;
        // #20;

        /*
        TEST 4: Input: 0x313233343536373839, Expected Output: 0x97
        */
        // rst = 0;
        // axiiv = 1'b1;
        // for (int i = 71; i >= 0; i = i - 8) begin
        //     axiid = test3[i -: 8];
        //     #20;
        // end
        // axiiv = 1'b0;
        // if (axiod == 8'h97) begin
        //     $display("TEST 4 PASSED");
        // end else begin 
        //     $display("TEST 4 FAILED");
        // end
        // $display("---------------------------");
        // #20;
        // rst = 1;
        // #400;

        /*
        TEST 5: Input: 0xHUGE, Expected Output: 0x00
        */
        rst = 0;
        axiiv = 1'b1;
        for (int i = 183; i >= 0; i = i - 8) begin
            axiid = test5[i -: 8];
            #20;
        end
        axiiv = 1'b0;
        if (axiod == 8'h00) begin
            $display("TEST 5 PASSED");
        end else begin 
            $display("TEST 5 FAILED");
        end
        $display("---------------------------");
        #20;
        rst = 1;
        #400;

        $display("Finishing Sim");
        $finish;
    end

endmodule

`default_nettype wire

fpga2/crcc.vcd
$date
	Sun Dec 11 14:03:01 2022
$end
$version
	Icarus Verilog
$end
$timescale
	1ps
$end
$scope module crcc_tb $end
$var wire 8 ! axiod [7:0] $end
$var reg 8 " axiid [7:0] $end
$var reg 1 # axiiv $end
$var reg 1 $ clk $end
$var reg 1 % rst $end
$var reg 1 & soft_reset_i $end
$var reg 16 ' test1 [15:0] $end
$var reg 32 ( test2 [31:0] $end
$var reg 72 ) test3 [71:0] $end
$var reg 184 * test5 [183:0] $end
$scope module my_crc_calc $end
$var wire 1 $ clk_i $end
$var wire 8 + crc_o [7:0] $end
$var wire 8 , data_i [7:0] $end
$var wire 1 % rst_i $end
$var wire 1 & soft_reset_i $end
$var wire 1 # valid_i $end
$var parameter 32 - CRC_SIZE $end
$var parameter 32 . DATA_WIDTH $end
$var parameter 64 / INIT $end
$var parameter 64 0 POLY $end
$var parameter 32 1 REF_IN $end
$var parameter 32 2 REF_OUT $end
$var parameter 64 3 XOR_OUT $end
$var reg 8 4 crc [7:0] $end
$var reg 8 5 crc_next [7:0] $end
$var reg 8 6 crc_prev [7:0] $end
$scope begin ref_out_ref_in $end
$scope begin $ivl_for_loop1 $end
$var integer 32 7 i [31:0] $end
$scope begin $ivl_for_loop2 $end
$var integer 32 8 j [31:0] $end
$upscope $end
$upscope $end
$upscope $end
$upscope $end
$scope begin $ivl_for_loop0 $end
$var integer 32 9 i [31:0] $end
$upscope $end
$upscope $end
$enddefinitions $end
$comment Show the parameter values. $end
$dumpall
b0 3
b1 2
b1 1
b11101 0
b11111111 /
b1000 .
b1000 -
$end
#0
$dumpvars
b0 9
b0 8
b0 7
bx 6
bx 5
bx 4
bx ,
bx +
b1010000100101001101110110010100100110000000000000000001000010011100110011011111111111001001100001110111010111010100110010010001000100000000110011000001000110111010010011100110111010001 *
b1100010011001000110011001101000011010100110110001101110011100000111001 )
b10010101010110011010011001101 (
b1111111111111111 '
x&
0%
0$
x#
bx "
bx !
$end
#10000
1$
#20000
0$
1%
#30000
b1000 7
b1000 8
bx 6
bx 5
b11111111 !
b11111111 +
b11111111 4
1$
#40000
0$
#50000
b11010001 !
b11010001 +
b11010001 4
b1000 8
b1000 7
b1100101 6
b1100101 5
1$
b10100001 "
b10100001 ,
b10110111 9
1#
0%
#60000
0$
#70000
b1101110 !
b1101110 +
b1101110 4
b1000 8
b1000 7
b10001 6
b10001 5
1$
b101001 "
b101001 ,
b10101111 9
#80000
0$
#90000
b1110110 !
b1110110 +
b1110110 4
b1000 8
b1000 7
b11010010 6
b11010010 5
1$
b10111011 "
b10111011 ,
b10100111 9
#100000
0$
#110000
b10110101 !
b10110101 +
b10110101 4
b1000 8
b1000 7
b11111101 6
b11111101 5
1$
b101001 "
b101001 ,
b10011111 9
#120000
0$
#130000
b111101 !
b111101 +
b111101 4
b1000 8
b1000 7
b110110 6
b110110 5
1$
b110000 "
b110000 ,
b10010111 9
#140000
0$
#150000
b1111 !
b1111 +
b1111 4
b1000 8
b1000 7
b11111110 6
b11111110 5
1$
b0 "
b0 ,
b10001111 9
#160000
0$
#170000
b110110 !
b110110 +
b110110 4
b1000 8
b1000 7
b11011000 6
b11011000 5
1$
b10 "
b10 ,
b10000111 9
#180000
0$
#190000
b10101011 !
b10101011 +
b10101011 4
b1000 8
b1000 7
b110010 6
b110010 5
1$
b10011 "
b10011 ,
b1111111 9
#200000
0$
#210000
b11110001 !
b11110001 +
b11110001 4
b1000 8
b1000 7
b11000001 6
b11000001 5
1$
b10011001 "
b10011001 ,
b1110111 9
#220000
0$
#230000
b11000110 !
b11000110 +
b11000110 4
b1000 8
b1000 7
b10110010 6
b10110010 5
1$
b10111111 "
b10111111 ,
b1101111 9
#240000
0$
#250000
b11000111 !
b11000111 +
b11000111 4
b1000 8
b1000 7
b10100011 6
b10100011 5
1$
b11111001 "
b11111001 ,
b1100111 9
#260000
0$
#270000
b10010000 !
b10010000 +
b10010000 4
b1000 8
b1000 7
b10010110 6
b10010110 5
1$
b110000 "
b110000 ,
b1011111 9
#280000
0$
#290000
b11111111 !
b11111111 +
b11111111 4
b1000 8
b1000 7
b1110011 6
b1110011 5
1$
b11101110 "
b11101110 ,
b1010111 9
#300000
0$
#310000
b11011001 !
b11011001 +
b11011001 4
b1000 8
b1000 7
b11011110 6
b11011110 5
1$
b10111010 "
b10111010 ,
b1001111 9
#320000
0$
#330000
b1011100 !
b1011100 +
b1011100 4
b1000 8
b1000 7
b1100001 6
b1100001 5
1$
b10011001 "
b10011001 ,
b1000111 9
#340000
0$
#350000
b11111111 !
b11111111 +
b11111111 4
b1000 8
b1000 7
b11000101 6
b11000101 5
1$
b100010 "
b100010 ,
b111111 9
#360000
0$
#370000
b1101 !
b1101 +
b1101 4
b1000 8
b1000 7
b11000 6
b11000 5
1$
b100000 "
b100000 ,
b110111 9
#380000
0$
#390000
b11110110 !
b11110110 +
b11110110 4
b1000 8
b1000 7
b110100 6
b110100 5
1$
b11001 "
b11001 ,
b101111 9
#400000
0$
#410000
b10000100 !
b10000100 +
b10000100 4
b1000 8
b1000 7
b101001 6
b101001 5
1$
b10000010 "
b10000010 ,
b100111 9
#420000
0$
#430000
b101101 !
b101101 +
b101101 4
b1000 8
b1000 7
b1101100 6
b1101100 5
1$
b110111 "
b110111 ,
b11111 9
#440000
0$
#450000
b10010011 !
b10010011 +
b10010011 4
b1000 8
b1000 7
b10001000 6
b10001000 5
1$
b1001001 "
b1001001 ,
b10111 9
#460000
0$
#470000
b11010001 !
b11010001 +
b11010001 4
b1000 8
b1000 7
b1000101 6
b1000101 5
1$
b11001101 "
b11001101 ,
b1111 9
#480000
0$
#490000
b0 !
b0 +
b0 4
b1000 8
b1000 7
b10010111 6
b10010111 5
1$
b11010001 "
b11010001 ,
b111 9
#500000
0$
#510000
1$
0#
b11111111111111111111111111111111 9
#520000
0$
#530000
b1000 8
b1000 7
b10110100 6
b10110100 5
b11111111 !
b11111111 +
b11111111 4
1$
1%
