fpga2/src/crcc.sv
`default_nettype none
`timescale 1ns / 1ps

`define SHIFT_IN (taxiod[7] ^ axiid)
`define TAPS 2, 3, 4

/*---------------------------------------------------------------------------------------------
* DESCRIPTION: This module implements CRC8, with the following
* formula G(x) = x^8 + x^4 + x^3 + x^2 + 1  
* width=8 poly=0x1d init=0xff refin=true refout=true xorout=0x00 check=0x97 residue=0x00
* THE DATA MUST COME IN LSB-MSByte!!!!
* ---------------------------------------------------------------------------------------------
*/
module crcc(clk, rst, axiiv, axiid, axiov, axiod);

	input logic clk, rst;
	input logic axiiv, axiid;

	output logic axiov;
	output logic[7:0] axiod;
	logic [7:0] taxiod, saxiod;   // We replace the AXI output with a placeholder variable
						  // This is done so that the AXI output can be bit-reversed, as it should according to CRC-EBU

	assign axiov = 1;

	always@(*) begin
		/* for every register in the lfsr, implement
		 * the schematic (giant case statement gets
		 * much smaller with macros, tastefully applied)
		 * we discuss above ...
		 */
		for (int i = 0; i < 8; i = i + 1) begin
			case (i)
			0: saxiod[i] = `SHIFT_IN;
			`TAPS: saxiod[i] = taxiod[i - 1] ^ `SHIFT_IN;
			default: saxiod[i] = taxiod[i - 1];
			endcase
		end

		/*	AXI output corresponds to the current bit-reversed value of
		 * 	the CRC. We loop to obtain this value.
		*/
		for (int k = 0; k < 8; k = k + 1) begin 
			 axiod[k] = taxiod[7 - k];
		end
	end

	always_ff @(posedge clk) begin
		/* init 0xFF */
		if (rst) taxiod <= 8'hFF;

		/* our output validity hinges on whether
		 * we are calculating anything or not
		 * on this clock cycle. if there is no
		 * valid input for us, don't do a shift
	 	 * this cycle
		 */
		else begin
			taxiod <= (axiiv) ? saxiod : taxiod;
		end
	end

endmodule

`default_nettype wire

fpga2/sim/crcc_tb.sv
`default_nettype none
`timescale 1ns / 1ps

module crcc_tb;
    logic clk;
    logic rst;
    logic axiiv;
    logic axiid;
    logic [7:0] axiid_alt;
    logic axiov;
    logic [7:0] axiod;

    crcc my_crcc(.clk(clk), .rst(rst), .axiiv(axiiv), .axiid(axiid), .axiov(axiov), .axiod(axiod));

    logic [15:0] test1 = 16'hFFFF;
    logic [31:0] test2 = 32'h12AB34CD;
    logic [71:0] test3 = 72'h313233343536373839;

    always begin
        #10;
        clk = !clk;
    end

    /* ---------------------------------------------------------------
     *  IMPORTANT NOTE:  
     *     THE INPUTS FOR THE CRC-8 HAVE TO BE BYTE-REVERSED
     *     IT IS SOMETHING TO TAKE INTO ACCOUNT WHEN VERIFYING THE CRC-8 TOO
     * ---------------------------------------------------------------
    */ 

    initial begin
        $dumpfile("crcc.vcd");
        $dumpvars(0, crcc_tb);
        $display("Starting Sim");
        clk = 0;
        rst = 0;
        #20;
        rst = 1;
        #30;
        rst = 0;

        /*
        TEST 1: Input: 0xFFFF, Expected Output: 0x23
        */
        axiiv = 1'b1;
        for (int i = 15; i >= 0; i = i - 8) begin
            axiid_alt = test1[i -: 8];
            for (int j = i - 7; j <= i; j = j + 1) begin
                axiid = test1[j];
                #20;
            end
        end
        axiiv = 1'b0;
        if (axiod == 8'h23) begin
            $display("TEST 1 PASSED");
        end else begin 
            $display("TEST 1 FAILED");
            $display("%h", axiod);
        end
        $display("---------------------------");
        #20;
        rst = 1;
        #20;

        /*
        TEST 2: Input: 0xCD, Expected Output: 0xF1
        */
        rst = 0;
        axiiv = 1'b1;
        for (int i = 7; i >= 0; i = i - 8) begin
            axiid_alt = test2[i -: 8];
            for (int j = i - 7; j <= i; j = j + 1) begin
                axiid = test2[j];
                #20;
            end
        end
        axiiv = 1'b0;
        if (axiod == 8'hF1) begin
            $display("TEST 2 PASSED");
        end else begin 
            $display("TEST 2 FAILED");
        end
        $display("---------------------------");
        #20;
        rst = 1;
        #20;

        /*
        TEST 3: Input: 0x12AB34CD, Expected Output: 0x6B
        */
        rst = 0;
        axiiv = 1'b1;
        for (int i = 31; i >= 0; i = i - 8) begin
            axiid_alt = test2[i -: 8];
            for (int j = i - 7; j <= i; j = j + 1) begin
                axiid = test2[j];
                #20;
            end
        end
        axiiv = 1'b0;
        if (axiod == 8'h6B) begin
            $display("TEST 3 PASSED");
        end else begin 
            $display("TEST 3 FAILED");
        end
        $display("---------------------------");
        #20;
        rst = 1;
        #20;

        /*
        TEST 4: Input: 0x313233343536373839, Expected Output: 0x97
        */
        rst = 0;
        axiiv = 1'b1;
        for (int i = 71; i >= 0; i = i - 8) begin
            axiid_alt = test3[i -: 8];
            for (int j = i - 7; j <= i; j = j + 1) begin
                axiid = test3[j];
                #20;
            end
        end
        axiiv = 1'b0;
        if (axiod == 8'h97) begin
            $display("TEST 4 PASSED");
        end else begin 
            $display("TEST 4 FAILED");
        end
        $display("---------------------------");
        #20;
        rst = 1;
        #400;

        $display("Finishing Sim");
        $finish;
    end

endmodule

`default_nettype wire

fpga2/crcc.vcd
$date
	Sat Dec 03 15:19:08 2022
$end
$version
	Icarus Verilog
$end
$timescale
	1ps
$end
$scope module crcc_tb $end
$var wire 1 ! axiov $end
$var wire 8 " axiod [7:0] $end
$var reg 1 # axiid $end
$var reg 8 $ axiid_alt [7:0] $end
$var reg 1 % axiiv $end
$var reg 1 & clk $end
$var reg 1 ' rst $end
$var reg 16 ( test1 [15:0] $end
$var reg 32 ) test2 [31:0] $end
$var reg 72 * test3 [71:0] $end
$scope module my_crcc $end
$var wire 1 # axiid $end
$var wire 1 % axiiv $end
$var wire 1 ! axiov $end
$var wire 1 & clk $end
$var wire 1 ' rst $end
$var reg 8 + axiod [7:0] $end
$var reg 8 , saxiod [7:0] $end
$var reg 8 - taxiod [7:0] $end
$scope begin $ivl_for_loop8 $end
$var integer 32 . i [31:0] $end
$upscope $end
$scope begin $ivl_for_loop9 $end
$var integer 32 / k [31:0] $end
$upscope $end
$upscope $end
$scope begin $ivl_for_loop0 $end
$var integer 32 0 i [31:0] $end
$scope begin $ivl_for_loop1 $end
$var integer 32 1 j [31:0] $end
$upscope $end
$upscope $end
$scope begin $ivl_for_loop2 $end
$var integer 32 2 i [31:0] $end
$scope begin $ivl_for_loop3 $end
$var integer 32 3 j [31:0] $end
$upscope $end
$upscope $end
$scope begin $ivl_for_loop4 $end
$var integer 32 4 i [31:0] $end
$scope begin $ivl_for_loop5 $end
$var integer 32 5 j [31:0] $end
$upscope $end
$upscope $end
$scope begin $ivl_for_loop6 $end
$var integer 32 6 i [31:0] $end
$scope begin $ivl_for_loop7 $end
$var integer 32 7 j [31:0] $end
$upscope $end
$upscope $end
$upscope $end
$enddefinitions $end
#0
$dumpvars
b0 7
b0 6
b0 5
b0 4
b0 3
b0 2
b0 1
b0 0
b0 /
b0 .
bx -
bx ,
bx +
b1100010011001000110011001101000011010100110110001101110011100000111001 *
b10010101010110011010011001101 )
b1111111111111111 (
0'
0&
x%
bx $
x#
bx "
1!
$end
#10000
1&
#20000
0&
1'
#30000
b1000 /
b11111111 "
b11111111 +
b111xxx1x ,
b1000 .
b11111111 -
1&
#40000
0&
#50000
b1111111 "
b1111111 +
b11111110 -
b1000 /
b11111100 ,
b1000 .
1&
1#
b1000 1
b11111111 $
b1111 0
1%
0'
#60000
0&
#70000
b111111 "
b111111 +
b1000 /
b11111000 ,
b1000 .
b11111100 -
1&
b1001 1
#80000
0&
#90000
b11111 "
b11111 +
b1000 /
b11110000 ,
b1000 .
b11111000 -
1&
b1010 1
#100000
0&
#110000
b1111 "
b1111 +
b1000 /
b11100000 ,
b1000 .
b11110000 -
1&
b1011 1
#120000
0&
#130000
b111 "
b111 +
b1000 /
b11000000 ,
b1000 .
b11100000 -
1&
b1100 1
#140000
0&
#150000
b11 "
b11 +
b1000 /
b10000000 ,
b1000 .
b11000000 -
1&
b1101 1
#160000
0&
#170000
b1 "
b1 +
b1000 /
b0 ,
b1000 .
b10000000 -
1&
b1110 1
#180000
0&
#190000
b0 "
b0 +
b1000 /
b11101 ,
b1000 .
b0 -
1&
b1111 1
#200000
0&
#210000
b10111000 "
b10111000 +
b1000 /
b100111 ,
b1000 .
b11101 -
1&
b111 0
b0 1
#220000
0&
#230000
b11100100 "
b11100100 +
b1000 /
b1010011 ,
b1000 .
b100111 -
1&
b1 1
#240000
0&
#250000
b11001010 "
b11001010 +
b1000 /
b10111011 ,
b1000 .
b1010011 -
1&
b10 1
#260000
0&
#270000
b11011101 "
b11011101 +
b1000 /
b1110110 ,
b1000 .
b10111011 -
1&
b11 1
#280000
0&
#290000
b1101110 "
b1101110 +
b1000 /
b11110001 ,
b1000 .
b1110110 -
1&
b100 1
#300000
0&
#310000
b10001111 "
b10001111 +
b1000 /
b11100010 ,
b1000 .
b11110001 -
1&
b101 1
#320000
0&
#330000
b1000111 "
b1000111 +
b1000 /
b11000100 ,
b1000 .
b11100010 -
1&
b110 1
#340000
0&
#350000
b100011 "
b100011 +
b1000 /
b10001000 ,
b1000 .
b11000100 -
1&
b111 1
#360000
0&
#370000
1&
0%
b11111111111111111111111111111111 0
b1000 1
#380000
0&
#390000
b11111111 "
b11111111 +
b1000 /
b11111110 ,
b1000 .
b11111111 -
1&
1'
#400000
0&
#410000
b1111111 "
b1111111 +
b1000 /
b11111100 ,
b1000 .
b11111110 -
1&
b11001101 $
b111 2
1%
0'
#420000
0&
#430000
b10000111 "
b10000111 +
b11100001 -
b1000 /
b11011111 ,
b1000 .
1&
0#
b1 3
#440000
0&
#450000
b1000011 "
b1000011 +
b11000010 -
b1000 /
b10000100 ,
b1000 .
1&
1#
b10 3
#460000
0&
#470000
b100001 "
b100001 +
b1000 /
b1000 ,
b1000 .
b10000100 -
1&
b11 3
#480000
0&
#490000
b10101000 "
b10101000 +
b10101 -
b1000 /
b101010 ,
b1000 .
1&
0#
b100 3
#500000
0&
#510000
b1010100 "
b1010100 +
b1000 /
b1010100 ,
b1000 .
b101010 -
1&
b101 3
#520000
0&
#530000
b10010010 "
b10010010 +
b1001001 -
b1000 /
b10001111 ,
b1000 .
1&
1#
b110 3
#540000
0&
#550000
b11110001 "
b11110001 +
b1000 /
b11110 ,
b1000 .
b10001111 -
1&
b111 3
#560000
0&
#570000
1&
0%
b11111111111111111111111111111111 2
b1000 3
#580000
0&
#590000
b11111111 "
b11111111 +
b1000 /
b11111110 ,
b1000 .
b11111111 -
1&
1'
#600000
0&
#610000
b11000111 "
b11000111 +
b11100011 -
b1000 /
b11011011 ,
b1000 .
1&
0#
b11000 5
b10010 $
b11111 4
1%
0'
#620000
0&
#630000
b1100011 "
b1100011 +
b11000110 -
b1000 /
b10001100 ,
b1000 .
1&
1#
b11001 5
#640000
0&
#650000
b10001001 "
b10001001 +
b10010001 -
b1000 /
b111111 ,
b1000 .
1&
0#
b11010 5
#660000
0&
#670000
b11111100 "
b11111100 +
b1000 /
b1111110 ,
b1000 .
b111111 -
1&
b11011 5
#680000
0&
#690000
b11000110 "
b11000110 +
b1100011 -
b1000 /
b11011011 ,
b1000 .
1&
1#
b11100 5
#700000
0&
#710000
b1100011 "
b1100011 +
b11000110 -
b1000 /
b10010001 ,
b1000 .
1&
0#
b11101 5
#720000
0&
#730000
b10001001 "
b10001001 +
b1000 /
b111111 ,
b1000 .
b10010001 -
1&
b11110 5
#740000
0&
#750000
b11111100 "
b11111100 +
b1000 /
b1111110 ,
b1000 .
b111111 -
1&
b11111 5
#760000
0&
#770000
b11000110 "
b11000110 +
b1100011 -
b1000 /
b11011011 ,
b1000 .
1&
1#
b10101011 $
b10111 4
b10000 5
#780000
0&
#790000
b11011011 "
b11011011 +
b1000 /
b10110110 ,
b1000 .
b11011011 -
1&
b10001 5
#800000
0&
#810000
b11010101 "
b11010101 +
b10101011 -
b1000 /
b1001011 ,
b1000 .
1&
0#
b10010 5
#820000
0&
#830000
b1101010 "
b1101010 +
b1010110 -
b1000 /
b10110001 ,
b1000 .
1&
1#
b10011 5
#840000
0&
#850000
b110101 "
b110101 +
b10101100 -
b1000 /
b1000101 ,
b1000 .
1&
0#
b10100 5
#860000
0&
#870000
b11010 "
b11010 +
b1011000 -
b1000 /
b10101101 ,
b1000 .
1&
1#
b10101 5
#880000
0&
#890000
b1101 "
b1101 +
b10110000 -
b1000 /
b1111101 ,
b1000 .
1&
0#
b10110 5
#900000
0&
#910000
b110 "
b110 +
b1100000 -
b1000 /
b11011101 ,
b1000 .
1&
1#
b10111 5
#920000
0&
#930000
b11 "
b11 +
b11000000 -
b1000 /
b10011101 ,
b1000 .
1&
0#
b110100 $
b1111 4
b1000 5
#940000
0&
#950000
b10111001 "
b10111001 +
b1000 /
b100111 ,
b1000 .
b10011101 -
1&
b1001 5
#960000
0&
#970000
b1011100 "
b1011100 +
b111010 -
b1000 /
b1101001 ,
b1000 .
1&
1#
b1010 5
#980000
0&
#990000
b101110 "
b101110 +
b1110100 -
b1000 /
b11101000 ,
b1000 .
1&
0#
b1011 5
#1000000
0&
#1010000
b10101111 "
b10101111 +
b11110101 -
b1000 /
b11101010 ,
b1000 .
1&
1#
b1100 5
#1020000
0&
#1030000
b1010111 "
b1010111 +
b1000 /
b11010100 ,
b1000 .
b11101010 -
1&
b1101 5
#1040000
0&
#1050000
b10010011 "
b10010011 +
b11001001 -
b1000 /
b10001111 ,
b1000 .
1&
0#
b1110 5
#1060000
0&
#1070000
b11110001 "
b11110001 +
b1000 /
b11 ,
b1000 .
b10001111 -
1&
b1111 5
#1080000
0&
#1090000
b1111000 "
b1111000 +
b11110 -
b1000 /
b100001 ,
b1000 .
1&
1#
b11001101 $
b111 4
b0 5
#1100000
0&
#1110000
b111100 "
b111100 +
b111100 -
b1000 /
b1111000 ,
b1000 .
1&
0#
b1 5
#1120000
0&
#1130000
b10100110 "
b10100110 +
b1100101 -
b1000 /
b11010111 ,
b1000 .
1&
1#
b10 5
#1140000
0&
#1150000
b11101011 "
b11101011 +
b1000 /
b10101110 ,
b1000 .
b11010111 -
1&
b11 5
#1160000
0&
#1170000
b11001101 "
b11001101 +
b10110011 -
b1000 /
b1111011 ,
b1000 .
1&
0#
b100 5
#1180000
0&
#1190000
b11011110 "
b11011110 +
b1000 /
b11110110 ,
b1000 .
b1111011 -
1&
b101 5
#1200000
0&
#1210000
b11010111 "
b11010111 +
b11101011 -
b1000 /
b11010110 ,
b1000 .
1&
1#
b110 5
#1220000
0&
#1230000
b1101011 "
b1101011 +
b1000 /
b10101100 ,
b1000 .
b11010110 -
1&
b111 5
#1240000
0&
#1250000
1&
0%
b11111111111111111111111111111111 4
b1000 5
#1260000
0&
#1270000
b11111111 "
b11111111 +
b1000 /
b11111110 ,
b1000 .
b11111111 -
1&
1'
#1280000
0&
#1290000
b1111111 "
b1111111 +
b1000 /
b11111100 ,
b1000 .
b11111110 -
1&
b1000000 7
b110001 $
b1000111 6
1%
0'
#1300000
0&
#1310000
b10000111 "
b10000111 +
b11100001 -
b1000 /
b11011111 ,
b1000 .
1&
0#
b1000001 7
#1320000
0&
#1330000
b11111011 "
b11111011 +
b1000 /
b10100011 ,
b1000 .
b11011111 -
1&
b1000010 7
#1340000
0&
#1350000
b11000101 "
b11000101 +
b1000 /
b1011011 ,
b1000 .
b10100011 -
1&
b1000011 7
#1360000
0&
#1370000
b1100010 "
b1100010 +
b1000110 -
b1000 /
b10010001 ,
b1000 .
1&
1#
b1000100 7
#1380000
0&
#1390000
b10001001 "
b10001001 +
b1000 /
b100010 ,
b1000 .
b10010001 -
1&
b1000101 7
#1400000
0&
#1410000
b11111100 "
b11111100 +
b111111 -
b1000 /
b1111110 ,
b1000 .
1&
0#
b1000110 7
#1420000
0&
#1430000
b1111110 "
b1111110 +
b1000 /
b11111100 ,
b1000 .
b1111110 -
1&
b1000111 7
#1440000
0&
#1450000
b111111 "
b111111 +
b1000 /
b11100101 ,
b1000 .
b11111100 -
1&
b110010 $
b111111 6
b111000 7
#1460000
0&
#1470000
b11111 "
b11111 +
b11111000 -
b1000 /
b11110000 ,
b1000 .
1&
1#
b111001 7
#1480000
0&
#1490000
b10110111 "
b10110111 +
b11101101 -
b1000 /
b11000111 ,
b1000 .
1&
0#
b111010 7
#1500000
0&
#1510000
b11100011 "
b11100011 +
b1000 /
b10010011 ,
b1000 .
b11000111 -
1&
b111011 7
#1520000
0&
#1530000
b1110001 "
b1110001 +
b10001110 -
b1000 /
b11100 ,
b1000 .
1&
1#
b111100 7
#1540000
0&
#1550000
b111000 "
b111000 +
b1000 /
b100101 ,
b1000 .
b11100 -
1&
b111101 7
#1560000
0&
#1570000
b11100 "
b11100 +
b111000 -
b1000 /
b1110000 ,
b1000 .
1&
0#
b111110 7
#1580000
0&
#1590000
b1110 "
b1110 +
b1000 /
b11100000 ,
b1000 .
b1110000 -
1&
b111111 7
#1600000
0&
#1610000
b10111111 "
b10111111 +
b11111101 -
b1000 /
b11111010 ,
b1000 .
1&
1#
b110011 $
b110111 6
b110000 7
#1620000
0&
#1630000
b1011111 "
b1011111 +
b1000 /
b11110100 ,
b1000 .
b11111010 -
1&
b110001 7
#1640000
0&
#1650000
b10010111 "
b10010111 +
b11101001 -
b1000 /
b11001111 ,
b1000 .
1&
0#
b110010 7
#1660000
0&
#1670000
b11110011 "
b11110011 +
b1000 /
b10000011 ,
b1000 .
b11001111 -
1&
b110011 7
#1680000
0&
#1690000
b1111001 "
b1111001 +
b10011110 -
b1000 /
b111100 ,
b1000 .
1&
1#
b110100 7
#1700000
0&
#1710000
b111100 "
b111100 +
b1000 /
b1100101 ,
b1000 .
b111100 -
1&
b110101 7
#1720000
0&
#1730000
b11110 "
b11110 +
b1111000 -
b1000 /
b11110000 ,
b1000 .
1&
0#
b110110 7
#1740000
0&
#1750000
b1111 "
b1111 +
b1000 /
b11111101 ,
b1000 .
b11110000 -
1&
b110111 7
#1760000
0&
#1770000
b10111111 "
b10111111 +
b1000 /
b11100111 ,
b1000 .
b11111101 -
1&
b110100 $
b101111 6
b101000 7
#1780000
0&
#1790000
b11100111 "
b11100111 +
b1000 /
b11010011 ,
b1000 .
b11100111 -
1&
b101001 7
#1800000
0&
#1810000
b1110011 "
b1110011 +
b11001110 -
b1000 /
b10011100 ,
b1000 .
1&
1#
b101010 7
#1820000
0&
#1830000
b10000001 "
b10000001 +
b10000001 -
b1000 /
b11111 ,
b1000 .
1&
0#
b101011 7
#1840000
0&
#1850000
b1000000 "
b1000000 +
b10 -
b1000 /
b11001 ,
b1000 .
1&
1#
b101100 7
#1860000
0&
#1870000
b10011000 "
b10011000 +
b1000 /
b101111 ,
b1000 .
b11001 -
1&
b101101 7
#1880000
0&
#1890000
b1001100 "
b1001100 +
b110010 -
b1000 /
b1100100 ,
b1000 .
1&
0#
b101110 7
#1900000
0&
#1910000
b100110 "
b100110 +
b1000 /
b11001000 ,
b1000 .
b1100100 -
1&
b101111 7
#1920000
0&
#1930000
b10101011 "
b10101011 +
b11010101 -
b1000 /
b10101010 ,
b1000 .
1&
1#
b110101 $
b100111 6
b100000 7
#1940000
0&
#1950000
b11101101 "
b11101101 +
b10110111 -
b1000 /
b1110011 ,
b1000 .
1&
0#
b100001 7
#1960000
0&
#1970000
b1110110 "
b1110110 +
b1101110 -
b1000 /
b11000001 ,
b1000 .
1&
1#
b100010 7
#1980000
0&
#1990000
b111011 "
b111011 +
b11011100 -
b1000 /
b10100101 ,
b1000 .
1&
0#
b100011 7
#2000000
0&
#2010000
b11101 "
b11101 +
b10111000 -
b1000 /
b1110000 ,
b1000 .
1&
1#
b100100 7
#2020000
0&
#2030000
b1110 "
b1110 +
b1000 /
b11111101 ,
b1000 .
b1110000 -
1&
b100101 7
#2040000
0&
#2050000
b111 "
b111 +
b11100000 -
b1000 /
b11011101 ,
b1000 .
1&
0#
b100110 7
#2060000
0&
#2070000
b10111011 "
b10111011 +
b1000 /
b10100111 ,
b1000 .
b11011101 -
1&
b100111 7
#2080000
0&
#2090000
b11100101 "
b11100101 +
b1000 /
b1010011 ,
b1000 .
b10100111 -
1&
b110110 $
b11111 6
b11000 7
#2100000
0&
#2110000
b1110010 "
b1110010 +
b1001110 -
b1000 /
b10000001 ,
b1000 .
1&
1#
b11001 7
#2120000
0&
#2130000
b10000001 "
b10000001 +
b1000 /
b10 ,
b1000 .
b10000001 -
1&
b11010 7
#2140000
0&
#2150000
b11111000 "
b11111000 +
b11111 -
b1000 /
b111110 ,
b1000 .
1&
0#
b11011 7
#2160000
0&
#2170000
b11000100 "
b11000100 +
b100011 -
b1000 /
b1011011 ,
b1000 .
1&
1#
b11100 7
#2180000
0&
#2190000
b11011010 "
b11011010 +
b1000 /
b10101011 ,
b1000 .
b1011011 -
1&
b11101 7
#2200000
0&
#2210000
b1101101 "
b1101101 +
b10110110 -
b1000 /
b1110001 ,
b1000 .
1&
0#
b11110 7
#2220000
0&
#2230000
b10001110 "
b10001110 +
b1000 /
b11100010 ,
b1000 .
b1110001 -
1&
b11111 7
#2240000
0&
#2250000
b11111111 "
b11111111 +
b11111111 -
b1000 /
b11111110 ,
b1000 .
1&
1#
b110111 $
b10111 6
b10000 7
#2260000
0&
#2270000
b1111111 "
b1111111 +
b1000 /
b11111100 ,
b1000 .
b11111110 -
1&
b10001 7
#2280000
0&
#2290000
b111111 "
b111111 +
b1000 /
b11111000 ,
b1000 .
b11111100 -
1&
b10010 7
#2300000
0&
#2310000
b10100111 "
b10100111 +
b11100101 -
b1000 /
b11010111 ,
b1000 .
1&
0#
b10011 7
#2320000
0&
#2330000
b1010011 "
b1010011 +
b11001010 -
b1000 /
b10010100 ,
b1000 .
1&
1#
b10100 7
#2340000
0&
#2350000
b101001 "
b101001 +
b1000 /
b101000 ,
b1000 .
b10010100 -
1&
b10101 7
#2360000
0&
#2370000
b10101100 "
b10101100 +
b110101 -
b1000 /
b1101010 ,
b1000 .
1&
0#
b10110 7
#2380000
0&
#2390000
b1010110 "
b1010110 +
b1000 /
b11010100 ,
b1000 .
b1101010 -
1&
b10111 7
#2400000
0&
#2410000
b101011 "
b101011 +
b1000 /
b10110101 ,
b1000 .
b11010100 -
1&
b111000 $
b1111 6
b1000 7
#2420000
0&
#2430000
b10101101 "
b10101101 +
b1000 /
b1110111 ,
b1000 .
b10110101 -
1&
b1001 7
#2440000
0&
#2450000
b11101110 "
b11101110 +
b1000 /
b11101110 ,
b1000 .
b1110111 -
1&
b1010 7
#2460000
0&
#2470000
b11001111 "
b11001111 +
b11110011 -
b1000 /
b11100110 ,
b1000 .
1&
1#
b1011 7
#2480000
0&
#2490000
b1100111 "
b1100111 +
b1000 /
b11001100 ,
b1000 .
b11100110 -
1&
b1100 7
#2500000
0&
#2510000
b110011 "
b110011 +
b1000 /
b10011000 ,
b1000 .
b11001100 -
1&
b1101 7
#2520000
0&
#2530000
b10100001 "
b10100001 +
b10000101 -
b1000 /
b10111 ,
b1000 .
1&
0#
b1110 7
#2540000
0&
#2550000
b11101000 "
b11101000 +
b1000 /
b101110 ,
b1000 .
b10111 -
1&
b1111 7
#2560000
0&
#2570000
b11001100 "
b11001100 +
b110011 -
b1000 /
b1111011 ,
b1000 .
1&
1#
b111001 $
b111 6
b0 7
#2580000
0&
#2590000
b1100110 "
b1100110 +
b1100110 -
b1000 /
b11001100 ,
b1000 .
1&
0#
b1 7
#2600000
0&
#2610000
b110011 "
b110011 +
b1000 /
b10000101 ,
b1000 .
b11001100 -
1&
b10 7
#2620000
0&
#2630000
b11001 "
b11001 +
b10011000 -
b1000 /
b110000 ,
b1000 .
1&
1#
b11 7
#2640000
0&
#2650000
b1100 "
b1100 +
b1000 /
b1111101 ,
b1000 .
b110000 -
1&
b100 7
#2660000
0&
#2670000
b10111110 "
b10111110 +
b1000 /
b11100111 ,
b1000 .
b1111101 -
1&
b101 7
#2680000
0&
#2690000
b1011111 "
b1011111 +
b11111010 -
b1000 /
b11101001 ,
b1000 .
1&
0#
b110 7
#2700000
0&
#2710000
b10010111 "
b10010111 +
b1000 /
b11001111 ,
b1000 .
b11101001 -
1&
b111 7
#2720000
0&
#2730000
1&
0%
b11111111111111111111111111111111 6
b1000 7
#2740000
0&
#2750000
b11111111 "
b11111111 +
b1000 /
b11100011 ,
b1000 .
b11111111 -
1&
1'
