fpga2/src/hardware_receiver.sv
`default_nettype none
`timescale 1ns / 1ps

module hardware_receiver(input wire clk, 
                input wire rst, 
                input wire din,
                
                output logic dout,
                output logic vout);

    logic [8:0] counter0;
    logic [8:0] counter1;
    always_ff@(posedge clk) begin
        if (rst) begin
            dout <= 0;
            vout <= 0;
        end else begin
            if (din) begin
                if (counter0 == 0 && counter1 < 8) begin
                    counter1 <= counter1 + 1;
                    vout <= 0;
                end else if (counter0 == 0 && counter1 == 8) begin
                    counter1 <= 0;
                    vout <= 1;
                    dout <= 1;
                end else begin
                    counter1 <= counter1 + 1;
                    counter0 <= 0;
                    vout <= 0;
                    dout <= 0;
                end
            end else begin
                if (counter1 == 0 && counter0 < 8) begin
                    counter0 <= counter0 + 1;
                    vout <= 0;
                end else if (counter1 == 0 && counter0 == 8) begin
                    counter0 <= 0;
                    vout <= 1;
                    dout <= 0;
                end else begin
                    counter0 <= counter0 + 1;
                    counter1 <= 0;
                    vout <= 0;
                    dout <= 0;
                end
            end
        end
    end

endmodule
`default_nettype wire

fpga2/sim/hardware_receiver_tb.sv
`default_nettype none
`timescale 1ns / 1ps

module hardware_receiver_tb;
    logic clk;
    logic rst;
    logic din;
    logic dout;
    logic vout;

    hardware_receiver my_receiver(.clk(clk), .rst(rst), .din(din), .dout(dout), .vout(vout));
    logic [59:0] data = 60'b1000000000_0000000000_0111111111_0000000000_0111111111_1111111111;

    always begin
        #10;
        clk = !clk;
    end

    initial begin
        $dumpfile("hardware_receiver.vcd");
        $dumpvars(0, hardware_receiver_tb);
        $display("Starting Sim");
        clk = 0;
        rst = 0;
        #20;
        rst = 1;
        #30;
        rst = 0;

        /*
        TEST 1: Input: 60'b1111111111_1111111111_0000000001_1111111111_1111111111_0000000000
        */
        for (int i = 0; i < 60; i = i + 1) begin
            din = data[59 - i];
            #20;
        end
        // #400;

        $display("Finishing Sim");
        $finish;
    end

endmodule

`default_nettype wire

fpga2/hardware_receiver.vcd
$date
	Fri Dec 09 21:19:14 2022
$end
$version
	Icarus Verilog
$end
$timescale
	1ps
$end
$scope module hardware_receiver_tb $end
$var wire 1 ! vout $end
$var wire 1 " dout $end
$var reg 1 # clk $end
$var reg 60 $ data [59:0] $end
$var reg 1 % din $end
$var reg 1 & rst $end
$scope module my_receiver $end
$var wire 1 # clk $end
$var wire 1 % din $end
$var wire 1 & rst $end
$var reg 9 ' counter0 [8:0] $end
$var reg 9 ( counter1 [8:0] $end
$var reg 1 " dout $end
$var reg 1 ! vout $end
$upscope $end
$scope begin $ivl_for_loop0 $end
$var integer 32 ) i [31:0] $end
$upscope $end
$upscope $end
$enddefinitions $end
$comment Show the parameter values. $end
$dumpall
$end
#0
$dumpvars
b0 )
bx (
bx '
0&
x%
b100000000000000000000111111111000000000001111111111111111111 $
0#
x"
x!
$end
#10000
0"
0!
b0 (
1#
#20000
0#
1&
#30000
1#
#40000
0#
#50000
b0 '
b1 (
1#
1%
0&
#60000
0#
#70000
b0 (
b1 '
1#
0%
b1 )
#80000
0#
#90000
b10 '
1#
b10 )
#100000
0#
#110000
b11 '
1#
b11 )
#120000
0#
#130000
b100 '
1#
b100 )
#140000
0#
#150000
b101 '
1#
b101 )
#160000
0#
#170000
b110 '
1#
b110 )
#180000
0#
#190000
b111 '
1#
b111 )
#200000
0#
#210000
b1000 '
1#
b1000 )
#220000
0#
#230000
1!
b0 '
1#
b1001 )
#240000
0#
#250000
0!
b1 '
1#
b1010 )
#260000
0#
#270000
b10 '
1#
b1011 )
#280000
0#
#290000
b11 '
1#
b1100 )
#300000
0#
#310000
b100 '
1#
b1101 )
#320000
0#
#330000
b101 '
1#
b1110 )
#340000
0#
#350000
b110 '
1#
b1111 )
#360000
0#
#370000
b111 '
1#
b10000 )
#380000
0#
#390000
b1000 '
1#
b10001 )
#400000
0#
#410000
1!
b0 '
1#
b10010 )
#420000
0#
#430000
0!
b1 '
1#
b10011 )
#440000
0#
#450000
b10 '
1#
b10100 )
#460000
0#
#470000
b0 '
b1 (
1#
1%
b10101 )
#480000
0#
#490000
b10 (
1#
b10110 )
#500000
0#
#510000
b11 (
1#
b10111 )
#520000
0#
#530000
b100 (
1#
b11000 )
#540000
0#
#550000
b101 (
1#
b11001 )
#560000
0#
#570000
b110 (
1#
b11010 )
#580000
0#
#590000
b111 (
1#
b11011 )
#600000
0#
#610000
b1000 (
1#
b11100 )
#620000
0#
#630000
1"
1!
b0 (
1#
b11101 )
#640000
0#
#650000
0!
b1 '
1#
0%
b11110 )
#660000
0#
#670000
b10 '
1#
b11111 )
#680000
0#
#690000
b11 '
1#
b100000 )
#700000
0#
#710000
b100 '
1#
b100001 )
#720000
0#
#730000
b101 '
1#
b100010 )
#740000
0#
#750000
b110 '
1#
b100011 )
#760000
0#
#770000
b111 '
1#
b100100 )
#780000
0#
#790000
b1000 '
1#
b100101 )
#800000
0#
#810000
0"
1!
b0 '
1#
b100110 )
#820000
0#
#830000
0!
b1 '
1#
b100111 )
#840000
0#
#850000
b10 '
1#
b101000 )
#860000
0#
#870000
b0 '
b1 (
1#
1%
b101001 )
#880000
0#
#890000
b10 (
1#
b101010 )
#900000
0#
#910000
b11 (
1#
b101011 )
#920000
0#
#930000
b100 (
1#
b101100 )
#940000
0#
#950000
b101 (
1#
b101101 )
#960000
0#
#970000
b110 (
1#
b101110 )
#980000
0#
#990000
b111 (
1#
b101111 )
#1000000
0#
#1010000
b1000 (
1#
b110000 )
#1020000
0#
#1030000
1"
1!
b0 (
1#
b110001 )
#1040000
0#
#1050000
0!
b1 (
1#
b110010 )
#1060000
0#
#1070000
b10 (
1#
b110011 )
#1080000
0#
#1090000
b11 (
1#
b110100 )
#1100000
0#
#1110000
b100 (
1#
b110101 )
#1120000
0#
#1130000
b101 (
1#
b110110 )
#1140000
0#
#1150000
b110 (
1#
b110111 )
#1160000
0#
#1170000
b111 (
1#
b111000 )
#1180000
0#
#1190000
b1000 (
1#
b111001 )
#1200000
0#
#1210000
1!
b0 (
1#
b111010 )
#1220000
0#
#1230000
0!
b1 (
1#
b111011 )
#1240000
0#
#1250000
b10 (
1#
b111100 )
