fpga2/src/hardware_receiver.sv
`default_nettype none
`timescale 1ns / 1ps

module hardware_receiver(input wire clk, 
                input wire rst, 
                input wire din,
                
                output logic dout,
                output logic vout);

    logic [8:0] counter0;
    logic [8:0] counter1;
    always_ff@(posedge clk) begin
        if (rst) begin
            dout <= 0;
            vout <= 0;
        end else begin
            if (din) begin
                if (counter0 == 0 && counter1 < 8) begin
                    counter1 <= counter1 + 1;
                    vout <= 0;
                end else if (counter0 == 0 && counter1 == 8) begin
                    counter1 <= 0;
                    vout <= 1;
                    dout <= 1;
                end else begin
                    counter1 <= counter1 + 1;
                    counter0 <= 0;
                    vout <= 0;
                    dout <= 0;
                end
            end else begin
                if (counter1 == 0 && counter0 < 8) begin
                    counter0 <= counter0 + 1;
                    vout <= 0;
                end else if (counter1 == 0 && counter0 == 8) begin
                    counter0 <= 0;
                    vout <= 1;
                    dout <= 0;
                end else begin
                    counter0 <= counter0 + 1;
                    counter1 <= 0;
                    vout <= 0;
                    dout <= 0;
                end
            end
        end
    end

endmodule
`default_nettype wire

fpga2/sim/hardware_receiver_tb.sv
`default_nettype none
`timescale 1ns / 1ps

module hardware_receiver_tb;
    logic clk;
    logic rst;
    logic din;
    logic dout;
    logic vout;

    hardware_receiver my_receiver(.clk(clk), .rst(rst), .din(din), .dout(dout), .vout(vout));
    logic [59:0] test1 = 60'b1000000000_0000000000_0111111111_0000000000_0111111111_1111111111;
    logic [99:0] test2 = 100'b1111111111_1111111111_0000000001_1111111111_1111111111_0000000000_0000000000_0000000000_0001111111_1111111111;

    always begin
        #10;
        clk = !clk;
    end

    initial begin
        $dumpfile("hardware_receiver.vcd");
        $dumpvars(0, hardware_receiver_tb);
        $display("Starting Sim");
        clk = 0;
        rst = 0;
        #20;
        rst = 1;
        #30;
        rst = 0;

        /*
        TEST 1: Input: 60'b1111111111_1111111111_0000000001_1111111111_1111111111_0000000000
        */
        // for (int i = 0; i < 60; i = i + 1) begin
        //     din = test1[59 - i];
        //     if (vout) begin
        //         $display(dout);
        //     end
        //     #20;
        // end
        // #400;

        /*
        TEST 2: Input: 100'b1111111111_1111111111_0000000001_1111111111_1111111111_0000000000_0000000000_0000000000_0001111111_1111111111;
        */
        for (int i = 0; i < 100; i = i + 1) begin
            din = test2[99 - i];
            if (vout) begin
                $display(dout);
            end
            #20;
        end
        // #400;

        $display("Finishing Sim");
        $finish;
    end

endmodule

`default_nettype wire

fpga2/hardware_receiver.vcd
$date
	Mon Dec 12 16:00:42 2022
$end
$version
	Icarus Verilog
$end
$timescale
	1ps
$end
$scope module hardware_receiver_tb $end
$var wire 1 ! vout $end
$var wire 1 " dout $end
$var reg 1 # clk $end
$var reg 1 $ din $end
$var reg 1 % rst $end
$var reg 60 & test1 [59:0] $end
$var reg 100 ' test2 [99:0] $end
$scope module my_receiver $end
$var wire 1 # clk $end
$var wire 1 $ din $end
$var wire 1 % rst $end
$var reg 9 ( counter0 [8:0] $end
$var reg 9 ) counter1 [8:0] $end
$var reg 1 " dout $end
$var reg 1 ! vout $end
$upscope $end
$scope begin $ivl_for_loop0 $end
$var integer 32 * i [31:0] $end
$upscope $end
$upscope $end
$enddefinitions $end
$comment Show the parameter values. $end
$dumpall
$end
#0
$dumpvars
b0 *
bx )
bx (
b1111111111111111111100000000011111111111111111111100000000000000000000000000000000011111111111111111 '
b100000000000000000000111111111000000000001111111111111111111 &
0%
x$
0#
x"
x!
$end
#10000
0"
0!
b0 )
1#
#20000
0#
1%
#30000
1#
#40000
0#
#50000
b0 (
b1 )
1#
1$
0%
#60000
0#
#70000
b10 )
1#
b1 *
#80000
0#
#90000
b11 )
1#
b10 *
#100000
0#
#110000
b100 )
1#
b11 *
#120000
0#
#130000
b101 )
1#
b100 *
#140000
0#
#150000
b110 )
1#
b101 *
#160000
0#
#170000
b111 )
1#
b110 *
#180000
0#
#190000
b1000 )
1#
b111 *
#200000
0#
#210000
1"
1!
b0 )
1#
b1000 *
#220000
0#
#230000
0!
b1 )
1#
b1001 *
#240000
0#
#250000
b10 )
1#
b1010 *
#260000
0#
#270000
b11 )
1#
b1011 *
#280000
0#
#290000
b100 )
1#
b1100 *
#300000
0#
#310000
b101 )
1#
b1101 *
#320000
0#
#330000
b110 )
1#
b1110 *
#340000
0#
#350000
b111 )
1#
b1111 *
#360000
0#
#370000
b1000 )
1#
b10000 *
#380000
0#
#390000
1!
b0 )
1#
b10001 *
#400000
0#
#410000
0!
b1 )
1#
b10010 *
#420000
0#
#430000
b10 )
1#
b10011 *
#440000
0#
#450000
0"
b0 )
b1 (
1#
0$
b10100 *
#460000
0#
#470000
b10 (
1#
b10101 *
#480000
0#
#490000
b11 (
1#
b10110 *
#500000
0#
#510000
b100 (
1#
b10111 *
#520000
0#
#530000
b101 (
1#
b11000 *
#540000
0#
#550000
b110 (
1#
b11001 *
#560000
0#
#570000
b111 (
1#
b11010 *
#580000
0#
#590000
b1000 (
1#
b11011 *
#600000
0#
#610000
1!
b0 (
1#
b11100 *
#620000
0#
#630000
0!
b1 )
1#
1$
b11101 *
#640000
0#
#650000
b10 )
1#
b11110 *
#660000
0#
#670000
b11 )
1#
b11111 *
#680000
0#
#690000
b100 )
1#
b100000 *
#700000
0#
#710000
b101 )
1#
b100001 *
#720000
0#
#730000
b110 )
1#
b100010 *
#740000
0#
#750000
b111 )
1#
b100011 *
#760000
0#
#770000
b1000 )
1#
b100100 *
#780000
0#
#790000
1"
1!
b0 )
1#
b100101 *
#800000
0#
#810000
0!
b1 )
1#
b100110 *
#820000
0#
#830000
b10 )
1#
b100111 *
#840000
0#
#850000
b11 )
1#
b101000 *
#860000
0#
#870000
b100 )
1#
b101001 *
#880000
0#
#890000
b101 )
1#
b101010 *
#900000
0#
#910000
b110 )
1#
b101011 *
#920000
0#
#930000
b111 )
1#
b101100 *
#940000
0#
#950000
b1000 )
1#
b101101 *
#960000
0#
#970000
1!
b0 )
1#
b101110 *
#980000
0#
#990000
0!
b1 )
1#
b101111 *
#1000000
0#
#1010000
b10 )
1#
b110000 *
#1020000
0#
#1030000
b11 )
1#
b110001 *
#1040000
0#
#1050000
0"
b0 )
b1 (
1#
0$
b110010 *
#1060000
0#
#1070000
b10 (
1#
b110011 *
#1080000
0#
#1090000
b11 (
1#
b110100 *
#1100000
0#
#1110000
b100 (
1#
b110101 *
#1120000
0#
#1130000
b101 (
1#
b110110 *
#1140000
0#
#1150000
b110 (
1#
b110111 *
#1160000
0#
#1170000
b111 (
1#
b111000 *
#1180000
0#
#1190000
b1000 (
1#
b111001 *
#1200000
0#
#1210000
1!
b0 (
1#
b111010 *
#1220000
0#
#1230000
0!
b1 (
1#
b111011 *
#1240000
0#
#1250000
b10 (
1#
b111100 *
#1260000
0#
#1270000
b11 (
1#
b111101 *
#1280000
0#
#1290000
b100 (
1#
b111110 *
#1300000
0#
#1310000
b101 (
1#
b111111 *
#1320000
0#
#1330000
b110 (
1#
b1000000 *
#1340000
0#
#1350000
b111 (
1#
b1000001 *
#1360000
0#
#1370000
b1000 (
1#
b1000010 *
#1380000
0#
#1390000
1!
b0 (
1#
b1000011 *
#1400000
0#
#1410000
0!
b1 (
1#
b1000100 *
#1420000
0#
#1430000
b10 (
1#
b1000101 *
#1440000
0#
#1450000
b11 (
1#
b1000110 *
#1460000
0#
#1470000
b100 (
1#
b1000111 *
#1480000
0#
#1490000
b101 (
1#
b1001000 *
#1500000
0#
#1510000
b110 (
1#
b1001001 *
#1520000
0#
#1530000
b111 (
1#
b1001010 *
#1540000
0#
#1550000
b1000 (
1#
b1001011 *
#1560000
0#
#1570000
1!
b0 (
1#
b1001100 *
#1580000
0#
#1590000
0!
b1 (
1#
b1001101 *
#1600000
0#
#1610000
b10 (
1#
b1001110 *
#1620000
0#
#1630000
b11 (
1#
b1001111 *
#1640000
0#
#1650000
b100 (
1#
b1010000 *
#1660000
0#
#1670000
b101 (
1#
b1010001 *
#1680000
0#
#1690000
b110 (
1#
b1010010 *
#1700000
0#
#1710000
b0 (
b1 )
1#
1$
b1010011 *
#1720000
0#
#1730000
b10 )
1#
b1010100 *
#1740000
0#
#1750000
b11 )
1#
b1010101 *
#1760000
0#
#1770000
b100 )
1#
b1010110 *
#1780000
0#
#1790000
b101 )
1#
b1010111 *
#1800000
0#
#1810000
b110 )
1#
b1011000 *
#1820000
0#
#1830000
b111 )
1#
b1011001 *
#1840000
0#
#1850000
b1000 )
1#
b1011010 *
#1860000
0#
#1870000
1"
1!
b0 )
1#
b1011011 *
#1880000
0#
#1890000
0!
b1 )
1#
b1011100 *
#1900000
0#
#1910000
b10 )
1#
b1011101 *
#1920000
0#
#1930000
b11 )
1#
b1011110 *
#1940000
0#
#1950000
b100 )
1#
b1011111 *
#1960000
0#
#1970000
b101 )
1#
b1100000 *
#1980000
0#
#1990000
b110 )
1#
b1100001 *
#2000000
0#
#2010000
b111 )
1#
b1100010 *
#2020000
0#
#2030000
b1000 )
1#
b1100011 *
#2040000
0#
#2050000
1!
b0 )
1#
b1100100 *
