fpga1/src/biphase.sv
`default_nettype none
`timescale 1ns / 1ps
// The clk should be around 6.144 MHZ clock which is twice the bit rate. This module should be 
//specifically used only for the bits after preamble  encoding of the main audio data
//Biphase encoding works as follows. For every logical input bit inputted in, the state of the data_output 
//will have two clock cycles. If the logical input is a 1, the state within that two clock cycle will be different
// if it is a 0, then the two    cycle will be the same. I am making the assumption that the beginning of biphase mark encoding
//i.e. the initlization does not matter and the similar or different states within two clock cycles are those which dictate the logcal 1 or 0   
module biphase (
            input wire logicalin, //Will be the same for two cycles 
            input wire newdatain,
            input wire previousbit,
            output logic biphaseout //remember this state is different between two clock cycles for 1   
); 

always@(*) begin //Double check later if this is the symbol combination 
    if (newdatain == 1) begin 
        biphaseout = ~previousbit;
    end else if (newdatain == 0) begin 
        if (logicalin == 0) begin 
            biphaseout = previousbit;
        end else 
        if (logicalin == 1) begin 
            biphaseout = ~previousbit;
        end 
    end  
end
endmodule
`default_nettype wire

fpga1/src/frame_assembly.sv
`timescale 1ns / 1ps
`default_nettype none

module frame_assembly(input wire clk, // 6.144 MHZ clock 
                   input wire rst,
                   input wire [19:0] din, // 20 bits from FIFO  
                   input wire vin, // data is valid 
                   input wire fifo_ready,  // ready signal from the FIFO that allows for frame assembly to start 
                                           // this will always be on; situations where it will be off are:
                                           // when the fifo is filling up at the begining, or when fifo runs out or command to stop 
                   output logic dout, // output data
                   output logic frame_ready // at the start of every frame (preamble) signal to say ready to get 20 bits from FIFO 
    );
    // NEED THIS: 28-bit SHIFT buffer ********************************************************************************* 

    logic previousbit; // this is for biphase and preamble 
    logic [7:0] frame_counter; // this variable counts the number of frames sent
    // The following counters keep track of the functioning of every subframe section
    logic [2:0] preamble_counter; // this variable counts the number of preamble bits sent. Counts up to 8  
    logic [2:0] aux_counter; // this variable counts the number of aux bits sent. Counts up to 8 because 4 logical bits * 2   
    logic[5:0] data_counter; // this variable counts the number of data bits sent. Counts up to 40 because 20 logical bits * 2   
    logic [1:0] valid_counter; 
    logic [1:0] user_counter;
    logic [1:0] channel_counter; 
    logic [1:0] parity_counter; 

    logic evenparitytracker; 
    logic EVENPARITYCOUNTER;  //TODO LATER TESTER TO SEE IF ITS 20? HOWEVER MANY PREAMBLE TO THE END BITS WIDE.  
    logic [1:0] channel_state; // This state variable defines the current channel from which information is being sent
    localparam CHANNEL_A = 2'b00;
    localparam CHANNEL_B = 2'b01;
    logic [191:0] channel = 192'b00000000_00010000_00000000_00000000_0100000000000000000000000000000000000000000000000000000000000000000000000000000000000000000000000000000000000000000000000000000000000000000000000000000000000000;

    // this state variable defines the current stage of the subframe
    typedef enum {PREAMBLE, AUX, DATA, VALID, USER, CHANNEL, PARITY} subframe_state;  
    subframe_state subframestate; 

    // set of preambles
    typedef enum bit [7:0] {START0 = 8'b11101000, START1 = 8'b00010111, LEFT0 = 8'b11100010, LEFT1 = 8'b00011101,
    RIGHT0 = 8'b11100100, RIGHT1 = 8'b00011011} preamble_state;  
    preamble_state preamblestate; 
    
    // biphase mark encoding transmitter
    logic logicalin; // the bit to be sent in BMC encoding over two clock cycles
    logic newdatain; 
    logic biphaseout; // dout in biphase-mark encoding 
    biphase mybiphase(.logicalin(logicalin), .newdatain(newdatain), .previousbit(previousbit), .biphaseout(biphaseout));

    always_ff@(posedge clk) begin
        if (rst || !fifo_ready) begin
            previousbit <= 0;  
            frame_counter <= 0; 
            subframestate <= PREAMBLE;
            channel_state <= CHANNEL_A; 
            frame_ready <= 0; 
            dout <= 0; 
            logicalin <= 0; 
            newdatain <= 0; // should be 0 at the end of preamble  
            preamble_counter <= 0;
            aux_counter <= 0; 
            data_counter <= 1; // we sent one already 
            valid_counter <= 1; // ????
            user_counter <= 1;  // ????
            channel_counter <= 1;
            parity_counter <= 1; 
            preamblestate <= START0;
            evenparitytracker <= 0; // check if this parity counter is working properly
        end else begin
            if (fifo_ready) begin 
                case(subframestate) 
                    PREAMBLE: // require framenumber and channel 
                    begin 
                        parity_counter <= 1; // FULL LOOP 

                        if (channel_state == CHANNEL_A) begin
                            preamble_counter <= preamble_counter + 1;
                            if (preamble_counter == 0) begin 
                                frame_ready <= 1; // POTENTIAL ERROR THAT FRAME IS NOT SEEN BY FIFO  we assume that for 8 cycles we will get back the data this is asking data from the FIFO                                 
                                if(frame_counter == 0) begin // this is the logic for the start bit 
                                    if (previousbit == 0)  begin 
                                        preamblestate <= START0;  
                                        dout <= START0[7]; 
                                        previousbit <= START0[7]; 
                                    end else
                                    if (previousbit == 1)  begin 
                                        preamblestate <= START1;  
                                        dout <= START1[7]; 
                                        previousbit <= START1[7]; 
                                    end  
                                end 
                                else begin // this is when it is not start of a block 
                                    if (previousbit == 0)  begin 
                                        preamblestate <= LEFT0;  
                                        dout <= LEFT0[7]; 
                                        previousbit <= LEFT0[7]; 
                                    end else
                                    if (previousbit == 1)  begin 
                                        preamblestate <= LEFT1;  
                                        dout <= LEFT1[7]; 
                                        previousbit <= LEFT1[7]; 
                                    end 
                                end 
                            end 
                      
                            // now we will begin to send the preamble
                            else if (preamble_counter < 8) begin 
                                frame_ready <= 0; 
                                dout <= preamblestate[7-preamble_counter]; 
                                previousbit <= preamblestate[7-preamble_counter];
                                if (preamble_counter == 7) begin 
                                    subframestate <= AUX;                                     
                                    logicalin <= 0; // this is the beginning of the biphase mark for AUX                                    
                                    evenparitytracker <= evenparitytracker ^ 0;
                                    newdatain <= 1;
                                end 
                            end    
                        end

                        else if (channel_state == CHANNEL_B) begin 
                            preamble_counter <= preamble_counter + 1; 
                            if (preamble_counter == 0) begin 
                                if (previousbit == 0)  begin 
                                    preamblestate <= RIGHT0;  
                                    dout <= RIGHT0[7]; 
                                    previousbit <= RIGHT0[7]; 
                                end else
                                if (previousbit == 1)  begin 
                                    preamblestate <= RIGHT1;  
                                    dout <= RIGHT1[7]; 
                                    previousbit <= RIGHT1[7]; 
                                end 
                            end
                             
                            else if (preamble_counter < 8) begin 
                                dout <= preamblestate[7-preamble_counter]; 
                                previousbit <= preamblestate[7-preamble_counter];
                                if (preamble_counter == 7) begin 
                                    subframestate <= AUX; 
                                    logicalin <= 0; // this is the beginning of the biphase mark for AUX                                    
                                    newdatain <= 1; // we changed this because on 1 it is offset by one clock cycle
                                    evenparitytracker <= evenparitytracker ^ 0;
                                end 
                            end                            
                        end 
                    end 
                    
                    AUX: 
                    begin 
                        preamble_counter <= 0;  
                        aux_counter <= aux_counter + 1; // counts to 8
                        if (aux_counter < 8) begin 
                            dout <= biphaseout;
                            previousbit <= biphaseout; 
                            newdatain <= ~newdatain;
                            if (aux_counter == 7) begin 
                                subframestate <= DATA; 
                                logicalin <= din[19]; // this is the beginning of the biphase mark for AUX                                    
                                evenparitytracker <= evenparitytracker ^ din[19];
                            end 
                        end                     
                    end

                    DATA: 
                    begin
                        aux_counter <= 0;  
                        data_counter <= data_counter + 1; // now counts to 40
                        // Current 0 
                        if (data_counter < 41) begin 
                            dout <= biphaseout;
                            previousbit <= biphaseout;                            
                            newdatain <= ~newdatain;
                            if (data_counter == 40) begin 
                                subframestate <= VALID; 
                                logicalin <= 0; // this is the beginning of the biphase mark for VALID      
                                evenparitytracker <= evenparitytracker ^ 0; 
                            // DOUBLE CHECK THIS WHEN AWAKE ERIC AND LOUIS FOR THE EVEN PARITY 
                            end else  begin 
                                if (~newdatain) begin 
                                    evenparitytracker <= evenparitytracker ^ din[19 - (data_counter >> 1)];
                                    logicalin <= din[19 - (data_counter >> 1)]; // MIGHT NOT WORK 
                                end 
                            end 
                        end
                    end

                    VALID: 
                    begin
                        dout <= biphaseout;
                        previousbit <= biphaseout;                            
                        data_counter <= 1;
                        valid_counter <= valid_counter + 1;  
                        newdatain <= ~newdatain;
                        if (valid_counter == 2) begin 
                            subframestate <= USER;
                            logicalin <= 0;
                            evenparitytracker <= evenparitytracker ^ 0; 
                        end
                    end

                    USER: 
                    begin
                        dout <= biphaseout;
                        previousbit <= biphaseout;                             
                        valid_counter <= 1;
                        user_counter <= user_counter + 1;  
                        newdatain <= ~newdatain;
                        if (user_counter == 2) begin 
                            subframestate <= CHANNEL;
                            logicalin <= channel[191 - frame_counter];
                            evenparitytracker <= evenparitytracker ^ channel[191 - frame_counter]; 
                        end
                    end

                    CHANNEL: 
                    begin 
                        dout <= biphaseout;
                        previousbit <= biphaseout;                            
                        user_counter <= 1;
                        channel_counter <= channel_counter + 1;  
                        newdatain <= ~newdatain;
                        if (channel_counter == 2) begin 
                            subframestate <= PARITY;
                            logicalin <= evenparitytracker; 
                        end
                    end

                    PARITY: 
                    begin 
                        dout <= biphaseout;
                        previousbit <= biphaseout;                            
                        newdatain <= ~newdatain;
                        channel_counter <= 1; 
                        parity_counter <= parity_counter + 1; 
                        evenparitytracker <= 0; 
                        if (parity_counter == 2) begin 
                            // newdatain <= 0; // FINAL TESTCASE see if at this moment it will be 0 
                            subframestate <= PREAMBLE; 
                            if (channel_state == CHANNEL_A) begin 
                                channel_state <= CHANNEL_B;
                            end                             
                            if (channel_state == CHANNEL_B) begin 
                                channel_state <= CHANNEL_A; 
                                if (frame_counter == 191) begin 
                                    frame_counter <= 0; 
                                end else begin 
                                    frame_counter <= frame_counter + 1;
                                end                                  
                            end 
                        end 
                    end

                    default: begin 
                    end  
                endcase 
            end
        end
    end
endmodule

`default_nettype wire

// todo NEED PREVIOUS BIT BEING SET FOR EVERYTHING AFTER PREAMBLE AND NEED DOUT TO GO TO BIPHASE OUT. 
// FOR PARITY WE NEED IT TO SEND OUT ONE BIT OF THE NEXT PREAMBLE 
// ALSO FOR PARITY STATE MACHINE WE NEED TO WE NEED THE LOGIC TO DECIDED WHICH OF THE PREAMBLE STATE WE CHOOSE IMMEDIATELY AS WELL. 
// wE ALSO NEED to have the channel 192 bits for channel // Eric will do this.

fpga1/sim/frame_assembly_tb.sv
`default_nettype none
`timescale 1ns / 1ps

module frame_assembly_tb;
    logic clk;
    logic rst;
    logic [19:0] din;
    logic vin;
    logic fifo_ready;
    logic dout;
    logic frame_ready;

    frame_assembly my_frame_assembly(.clk(clk), .rst(rst), .din(din), .vin(vin), .fifo_ready(fifo_ready), .dout(dout), .frame_ready(frame_ready));

    logic [19:0] test1 = 20'hFFFFE;

    // set of preambles
    typedef enum bit [7:0] {START0 = 8'b11101000, START1 = 8'b00010111, LEFT0 = 8'b11100010, LEFT1 = 8'b00011101,
    RIGHT0 = 8'b11100100, RIGHT1 = 8'b00011011} preamble_state;  
    preamble_state preamblestate; 
    logic fail;

    always begin
        #10;
        clk = !clk;
    end

    initial begin
        $dumpfile("frame_assembly.vcd");
        $dumpvars(0, frame_assembly_tb);
        $display("Starting Sim");
        clk = 0;
        rst = 0;
        #20;
        rst = 1;
        #20;
        rst = 0;
        #30;

        /* ---------------------------------------------------------------
        *  TEST 1: Pull cable through the PREAMBLE; fifo_ready signal goes 
        *  down immediately.
        *  INSTRUCTIONS:
        *   - Check multiple values for the channel_state, the initial previousbit, and the frame_counter
        *  ---------------------------------------------------------------
        */ 
        // fifo_ready = 1;
        // din = test1;

        // preamblestate = START0;
        // fail = 0;
        // for (integer i = 0; i < 5; i = i + 1) begin
        //     if (dout != preamblestate[7 - i]) begin
        //         // $display("TEST 1 FAILED");
        //         fail = 1;
        //     end
        //     if (i == 4) begin
        //         fifo_ready = 0;
        //     end
        //     #20;
        // end
        // if (!fail || dout == 0) begin
        //     // $display("TEST 1 PASSED");
        // end else begin
        //     // $display("TEST 1 FAILED");
        // end
        // #300;

        /* ---------------------------------------------------------------
        *  TEST 2: We send just A's as data, check for any first issues
        *  In this test case, we comment out everything except the preamble
        *  and make sure that the preamble is working.
        *       - Check if the starting bits are working
        *       - Check for transitions
        *       - Check for block transitions
        *  ---------------------------------------------------------------
        */
        fail = 0;
        preamblestate = START0;
        fifo_ready = 1;
        din = test1;
        $display("%h", test1);
        $display("%b", test1);
        // for (integer i = 0; i < 8; i = i + 1) begin
        //     if (dout != preamblestate[i]) begin
        //         $display("TEST 1 FAILED");
        //         fail = 1;
        //     end
        //     #20;
        // end
        // if (!fail) begin
        //     $display("TEST 1 PASSED");
        // end
        #500000;

        /*
        NOTE: TEST MORE ROBUSTLY LATER ON
        */

        $display("Finishing Sim");
        $finish;
    end

endmodule

`default_nettype wire

fpga1/frame_assembly.vcd
$date
	Wed Nov 30 21:43:31 2022
$end
$version
	Icarus Verilog
$end
$timescale
	1ps
$end
$scope module frame_assembly_tb $end
$var wire 1 ! frame_ready $end
$var wire 1 " dout $end
$var reg 1 # clk $end
$var reg 20 $ din [19:0] $end
$var reg 1 % fail $end
$var reg 1 & fifo_ready $end
$var reg 1 ' rst $end
$var reg 20 ( test1 [19:0] $end
$var reg 1 ) vin $end
$var reg 8 * preamblestate [7:0] $end
$scope module my_frame_assembly $end
$var wire 1 # clk $end
$var wire 20 + din [19:0] $end
$var wire 1 & fifo_ready $end
$var wire 1 ' rst $end
$var wire 1 ) vin $end
$var wire 1 , biphaseout $end
$var reg 3 - aux_counter [2:0] $end
$var reg 192 . channel [191:0] $end
$var reg 2 / channel_counter [1:0] $end
$var reg 2 0 channel_state [1:0] $end
$var reg 6 1 data_counter [5:0] $end
$var reg 1 " dout $end
$var reg 1 2 evenparitytracker $end
$var reg 8 3 frame_counter [7:0] $end
$var reg 1 ! frame_ready $end
$var reg 1 4 logicalin $end
$var reg 1 5 newdatain $end
$var reg 2 6 parity_counter [1:0] $end
$var reg 3 7 preamble_counter [2:0] $end
$var reg 1 8 previousbit $end
$var reg 2 9 user_counter [1:0] $end
$var reg 2 : valid_counter [1:0] $end
$var reg 8 ; preamblestate [7:0] $end
$var integer 32 < subframestate [31:0] $end
$scope module mybiphase $end
$var wire 1 4 logicalin $end
$var wire 1 5 newdatain $end
$var wire 1 8 previousbit $end
$var reg 1 , biphaseout $end
$upscope $end
$upscope $end
$upscope $end
$enddefinitions $end
#0
$dumpvars
b0 <
b0 ;
bx :
bx 9
x8
bx 7
bx 6
x5
x4
bx 3
x2
bx 1
bx 0
bx /
b1000000000000000000000100000000000000000000000000000000000000000000000000000000000000000000000000000000000000000000000000000000000000000000000000000000000000000000000000000000000000 .
bx -
x,
bx +
b0 *
x)
b11111111111111111110 (
0'
x&
x%
bx $
0#
x"
x!
$end
#10000
1#
#20000
0#
1'
#30000
0,
02
b11101000 ;
b1 6
b1 /
b1 9
b1 :
b1 1
b0 -
b0 7
05
04
0"
0!
b0 0
b0 3
08
1#
#40000
0#
0'
#50000
1#
#60000
0#
#70000
1,
18
1"
1!
b1 7
1#
b11111111111111111110 $
b11111111111111111110 +
1&
b11101000 *
0%
#80000
0#
#90000
0!
b10 7
1#
#100000
0#
#110000
b11 7
1#
#120000
0#
#130000
0,
08
0"
b100 7
1#
#140000
0#
#150000
1,
18
1"
b101 7
1#
#160000
0#
#170000
0,
08
0"
b110 7
1#
#180000
0#
#190000
b111 7
1#
#200000
0#
#210000
1,
15
b1 <
b0 7
1#
#220000
0#
#230000
05
18
1"
b1 -
1#
#240000
0#
#250000
0,
15
b10 -
1#
#260000
0#
#270000
05
08
0"
b11 -
1#
#280000
0#
#290000
1,
15
b100 -
1#
#300000
0#
#310000
05
18
1"
b101 -
1#
#320000
0#
#330000
0,
15
b110 -
1#
#340000
0#
#350000
05
08
0"
b111 -
1#
#360000
0#
#370000
1,
12
14
b10 <
15
b0 -
1#
#380000
0#
#390000
0,
05
18
1"
b10 1
1#
#400000
0#
#410000
1,
02
15
08
0"
b11 1
1#
#420000
0#
#430000
0,
05
18
1"
b100 1
1#
#440000
0#
#450000
1,
12
15
08
0"
b101 1
1#
#460000
0#
#470000
0,
05
18
1"
b110 1
1#
#480000
0#
#490000
1,
02
15
08
0"
b111 1
1#
#500000
0#
#510000
0,
05
18
1"
b1000 1
1#
#520000
0#
#530000
1,
12
15
08
0"
b1001 1
1#
#540000
0#
#550000
0,
05
18
1"
b1010 1
1#
#560000
0#
#570000
1,
02
15
08
0"
b1011 1
1#
#580000
0#
#590000
0,
05
18
1"
b1100 1
1#
#600000
0#
#610000
1,
12
15
08
0"
b1101 1
1#
#620000
0#
#630000
0,
05
18
1"
b1110 1
1#
#640000
0#
#650000
1,
02
15
08
0"
b1111 1
1#
#660000
0#
#670000
0,
05
18
1"
b10000 1
1#
#680000
0#
#690000
1,
12
15
08
0"
b10001 1
1#
#700000
0#
#710000
0,
05
18
1"
b10010 1
1#
#720000
0#
#730000
1,
02
15
08
0"
b10011 1
1#
#740000
0#
#750000
0,
05
18
1"
b10100 1
1#
#760000
0#
#770000
1,
12
15
08
0"
b10101 1
1#
#780000
0#
#790000
0,
05
18
1"
b10110 1
1#
#800000
0#
#810000
1,
02
15
08
0"
b10111 1
1#
#820000
0#
#830000
0,
05
18
1"
b11000 1
1#
#840000
0#
#850000
1,
12
15
08
0"
b11001 1
1#
#860000
0#
#870000
0,
05
18
1"
b11010 1
1#
#880000
0#
#890000
1,
02
15
08
0"
b11011 1
1#
#900000
0#
#910000
0,
05
18
1"
b11100 1
1#
#920000
0#
#930000
1,
12
15
08
0"
b11101 1
1#
#940000
0#
#950000
0,
05
18
1"
b11110 1
1#
#960000
0#
#970000
1,
02
15
08
0"
b11111 1
1#
#980000
0#
#990000
0,
05
18
1"
b100000 1
1#
#1000000
0#
#1010000
1,
12
15
08
0"
b100001 1
1#
#1020000
0#
#1030000
0,
05
18
1"
b100010 1
1#
#1040000
0#
#1050000
1,
02
15
08
0"
b100011 1
1#
#1060000
0#
#1070000
0,
05
18
1"
b100100 1
1#
#1080000
0#
#1090000
1,
12
15
08
0"
b100101 1
1#
#1100000
0#
#1110000
0,
05
18
1"
b100110 1
1#
#1120000
0#
#1130000
1,
04
15
08
0"
b100111 1
1#
#1140000
0#
#1150000
05
18
1"
b101000 1
1#
#1160000
0#
#1170000
0,
b11 <
15
b101001 1
1#
#1180000
0#
#1190000
05
b10 :
b1 1
08
0"
1#
#1200000
0#
#1210000
1,
b100 <
15
b11 :
1#
#1220000
0#
#1230000
05
b10 9
b1 :
18
1"
1#
#1240000
0#
#1250000
0,
b101 <
15
b11 9
1#
#1260000
0#
#1270000
05
b10 /
b1 9
08
0"
1#
#1280000
0#
#1290000
1,
14
b110 <
15
b11 /
1#
#1300000
0#
#1310000
0,
02
b10 6
b1 /
05
18
1"
1#
#1320000
0#
#1330000
1,
b1 0
b0 <
b11 6
15
08
0"
1#
#1340000
0#
#1350000
0,
18
1"
b11100100 ;
b1 7
b1 6
1#
#1360000
0#
#1370000
b10 7
1#
#1380000
0#
#1390000
b11 7
1#
#1400000
0#
#1410000
1,
08
0"
b100 7
1#
#1420000
0#
#1430000
b101 7
1#
#1440000
0#
#1450000
0,
18
1"
b110 7
1#
#1460000
0#
#1470000
1,
08
0"
b111 7
1#
#1480000
0#
#1490000
04
b1 <
b0 7
1#
#1500000
0#
#1510000
05
18
1"
b1 -
1#
#1520000
0#
#1530000
0,
15
b10 -
1#
#1540000
0#
#1550000
05
08
0"
b11 -
1#
#1560000
0#
#1570000
1,
15
b100 -
1#
#1580000
0#
#1590000
05
18
1"
b101 -
1#
#1600000
0#
#1610000
0,
15
b110 -
1#
#1620000
0#
#1630000
05
08
0"
b111 -
1#
#1640000
0#
#1650000
1,
12
14
b10 <
15
b0 -
1#
#1660000
0#
#1670000
0,
05
18
1"
b10 1
1#
#1680000
0#
#1690000
1,
02
15
08
0"
b11 1
1#
#1700000
0#
#1710000
0,
05
18
1"
b100 1
1#
#1720000
0#
#1730000
1,
12
15
08
0"
b101 1
1#
#1740000
0#
#1750000
0,
05
18
1"
b110 1
1#
#1760000
0#
#1770000
1,
02
15
08
0"
b111 1
1#
#1780000
0#
#1790000
0,
05
18
1"
b1000 1
1#
#1800000
0#
#1810000
1,
12
15
08
0"
b1001 1
1#
#1820000
0#
#1830000
0,
05
18
1"
b1010 1
1#
#1840000
0#
#1850000
1,
02
15
08
0"
b1011 1
1#
#1860000
0#
#1870000
0,
05
18
1"
b1100 1
1#
#1880000
0#
#1890000
1,
12
15
08
0"
b1101 1
1#
#1900000
0#
#1910000
0,
05
18
1"
b1110 1
1#
#1920000
0#
#1930000
1,
02
15
08
0"
b1111 1
1#
#1940000
0#
#1950000
0,
05
18
1"
b10000 1
1#
#1960000
0#
#1970000
1,
12
15
08
0"
b10001 1
1#
#1980000
0#
#1990000
0,
05
18
1"
b10010 1
1#
#2000000
0#
#2010000
1,
02
15
08
0"
b10011 1
1#
#2020000
0#
#2030000
0,
05
18
1"
b10100 1
1#
#2040000
0#
#2050000
1,
12
15
08
0"
b10101 1
1#
#2060000
0#
#2070000
0,
05
18
1"
b10110 1
1#
#2080000
0#
#2090000
1,
02
15
08
0"
b10111 1
1#
#2100000
0#
#2110000
0,
05
18
1"
b11000 1
1#
#2120000
0#
#2130000
1,
12
15
08
0"
b11001 1
1#
#2140000
0#
#2150000
0,
05
18
1"
b11010 1
1#
#2160000
0#
#2170000
1,
02
15
08
0"
b11011 1
1#
#2180000
0#
#2190000
0,
05
18
1"
b11100 1
1#
#2200000
0#
#2210000
1,
12
15
08
0"
b11101 1
1#
#2220000
0#
#2230000
0,
05
18
1"
b11110 1
1#
#2240000
0#
#2250000
1,
02
15
08
0"
b11111 1
1#
#2260000
0#
#2270000
0,
05
18
1"
b100000 1
1#
#2280000
0#
#2290000
1,
12
15
08
0"
b100001 1
1#
#2300000
0#
#2310000
0,
05
18
1"
b100010 1
1#
#2320000
0#
#2330000
1,
02
15
08
0"
b100011 1
1#
#2340000
0#
#2350000
0,
05
18
1"
b100100 1
1#
#2360000
0#
#2370000
1,
12
15
08
0"
b100101 1
1#
#2380000
0#
#2390000
0,
05
18
1"
b100110 1
1#
#2400000
0#
#2410000
1,
04
15
08
0"
b100111 1
1#
#2420000
0#
#2430000
05
18
1"
b101000 1
1#
#2440000
0#
#2450000
0,
b11 <
15
b101001 1
1#
#2460000
0#
#2470000
05
b10 :
b1 1
08
0"
1#
#2480000
0#
#2490000
1,
b100 <
15
b11 :
1#
#2500000
0#
#2510000
05
b10 9
b1 :
18
1"
1#
#2520000
0#
#2530000
0,
b101 <
15
b11 9
1#
#2540000
0#
#2550000
05
b10 /
b1 9
08
0"
1#
#2560000
0#
#2570000
1,
14
b110 <
15
b11 /
1#
#2580000
0#
#2590000
0,
02
b10 6
b1 /
05
18
1"
1#
#2600000
0#
#2610000
1,
b1 3
b0 0
b0 <
b11 6
15
08
0"
1#
#2620000
0#
#2630000
0,
18
1"
b11100010 ;
1!
b1 7
b1 6
1#
#2640000
0#
#2650000
0!
b10 7
1#
#2660000
0#
#2670000
b11 7
1#
#2680000
0#
#2690000
1,
08
0"
b100 7
1#
#2700000
0#
#2710000
b101 7
1#
#2720000
0#
#2730000
b110 7
1#
#2740000
0#
#2750000
0,
18
1"
b111 7
1#
#2760000
0#
#2770000
1,
04
b1 <
08
0"
b0 7
1#
#2780000
0#
#2790000
05
18
1"
b1 -
1#
#2800000
0#
#2810000
0,
15
b10 -
1#
#2820000
0#
#2830000
05
08
0"
b11 -
1#
#2840000
0#
#2850000
1,
15
b100 -
1#
#2860000
0#
#2870000
05
18
1"
b101 -
1#
#2880000
0#
#2890000
0,
15
b110 -
1#
#2900000
0#
#2910000
05
08
0"
b111 -
1#
#2920000
0#
#2930000
1,
12
14
b10 <
15
b0 -
1#
#2940000
0#
#2950000
0,
05
18
1"
b10 1
1#
#2960000
0#
#2970000
1,
02
15
08
0"
b11 1
1#
#2980000
0#
#2990000
0,
05
18
1"
b100 1
1#
#3000000
0#
#3010000
1,
12
15
08
0"
b101 1
1#
#3020000
0#
#3030000
0,
05
18
1"
b110 1
1#
#3040000
0#
#3050000
1,
02
15
08
0"
b111 1
1#
#3060000
0#
#3070000
0,
05
18
1"
b1000 1
1#
#3080000
0#
#3090000
1,
12
15
08
0"
b1001 1
1#
#3100000
0#
#3110000
0,
05
18
1"
b1010 1
1#
#3120000
0#
#3130000
1,
02
15
08
0"
b1011 1
1#
#3140000
0#
#3150000
0,
05
18
1"
b1100 1
1#
#3160000
0#
#3170000
1,
12
15
08
0"
b1101 1
1#
#3180000
0#
#3190000
0,
05
18
1"
b1110 1
1#
#3200000
0#
#3210000
1,
02
15
08
0"
b1111 1
1#
#3220000
0#
#3230000
0,
05
18
1"
b10000 1
1#
#3240000
0#
#3250000
1,
12
15
08
0"
b10001 1
1#
#3260000
0#
#3270000
0,
05
18
1"
b10010 1
1#
#3280000
0#
#3290000
1,
02
15
08
0"
b10011 1
1#
#3300000
0#
#3310000
0,
05
18
1"
b10100 1
1#
#3320000
0#
#3330000
1,
12
15
08
0"
b10101 1
1#
#3340000
0#
#3350000
0,
05
18
1"
b10110 1
1#
#3360000
0#
#3370000
1,
02
15
08
0"
b10111 1
1#
#3380000
0#
#3390000
0,
05
18
1"
b11000 1
1#
#3400000
0#
#3410000
1,
12
15
08
0"
b11001 1
1#
#3420000
0#
#3430000
0,
05
18
1"
b11010 1
1#
#3440000
0#
#3450000
1,
02
15
08
0"
b11011 1
1#
#3460000
0#
#3470000
0,
05
18
1"
b11100 1
1#
#3480000
0#
#3490000
1,
12
15
08
0"
b11101 1
1#
#3500000
0#
#3510000
0,
05
18
1"
b11110 1
1#
#3520000
0#
#3530000
1,
02
15
08
0"
b11111 1
1#
#3540000
0#
#3550000
0,
05
18
1"
b100000 1
1#
#3560000
0#
#3570000
1,
12
15
08
0"
b100001 1
1#
#3580000
0#
#3590000
0,
05
18
1"
b100010 1
1#
#3600000
0#
#3610000
1,
02
15
08
0"
b100011 1
1#
#3620000
0#
#3630000
0,
05
18
1"
b100100 1
1#
#3640000
0#
#3650000
1,
12
15
08
0"
b100101 1
1#
#3660000
0#
#3670000
0,
05
18
1"
b100110 1
1#
#3680000
0#
#3690000
1,
04
15
08
0"
b100111 1
1#
#3700000
0#
#3710000
05
18
1"
b101000 1
1#
#3720000
0#
#3730000
0,
b11 <
15
b101001 1
1#
#3740000
0#
#3750000
05
b10 :
b1 1
08
0"
1#
#3760000
0#
#3770000
1,
b100 <
15
b11 :
1#
#3780000
0#
#3790000
05
b10 9
b1 :
18
1"
1#
#3800000
0#
#3810000
0,
b101 <
15
b11 9
1#
#3820000
0#
#3830000
05
b10 /
b1 9
08
0"
1#
#3840000
0#
#3850000
1,
14
b110 <
15
b11 /
1#
#3860000
0#
#3870000
0,
02
b10 6
b1 /
05
18
1"
1#
#3880000
0#
#3890000
1,
b1 0
b0 <
b11 6
15
08
0"
1#
#3900000
0#
#3910000
0,
18
1"
b11100100 ;
b1 7
b1 6
1#
#3920000
0#
#3930000
b10 7
1#
#3940000
0#
#3950000
b11 7
1#
#3960000
0#
#3970000
1,
08
0"
b100 7
1#
#3980000
0#
#3990000
b101 7
1#
#4000000
0#
#4010000
0,
18
1"
b110 7
1#
#4020000
0#
#4030000
1,
08
0"
b111 7
1#
#4040000
0#
#4050000
04
b1 <
b0 7
1#
#4060000
0#
#4070000
05
18
1"
b1 -
1#
#4080000
0#
#4090000
0,
15
b10 -
1#
#4100000
0#
#4110000
05
08
0"
b11 -
1#
#4120000
0#
#4130000
1,
15
b100 -
1#
#4140000
0#
#4150000
05
18
1"
b101 -
1#
#4160000
0#
#4170000
0,
15
b110 -
1#
#4180000
0#
#4190000
05
08
0"
b111 -
1#
#4200000
0#
#4210000
1,
12
14
b10 <
15
b0 -
1#
#4220000
0#
#4230000
0,
05
18
1"
b10 1
1#
#4240000
0#
#4250000
1,
02
15
08
0"
b11 1
1#
#4260000
0#
#4270000
0,
05
18
1"
b100 1
1#
#4280000
0#
#4290000
1,
12
15
08
0"
b101 1
1#
#4300000
0#
#4310000
0,
05
18
1"
b110 1
1#
#4320000
0#
#4330000
1,
02
15
08
0"
b111 1
1#
#4340000
0#
#4350000
0,
05
18
1"
b1000 1
1#
#4360000
0#
#4370000
1,
12
15
08
0"
b1001 1
1#
#4380000
0#
#4390000
0,
05
18
1"
b1010 1
1#
#4400000
0#
#4410000
1,
02
15
08
0"
b1011 1
1#
#4420000
0#
#4430000
0,
05
18
1"
b1100 1
1#
#4440000
0#
#4450000
1,
12
15
08
0"
b1101 1
1#
#4460000
0#
#4470000
0,
05
18
1"
b1110 1
1#
#4480000
0#
#4490000
1,
02
15
08
0"
b1111 1
1#
#4500000
0#
#4510000
0,
05
18
1"
b10000 1
1#
#4520000
0#
#4530000
1,
12
15
08
0"
b10001 1
1#
#4540000
0#
#4550000
0,
05
18
1"
b10010 1
1#
#4560000
0#
#4570000
1,
02
15
08
0"
b10011 1
1#
#4580000
0#
#4590000
0,
05
18
1"
b10100 1
1#
#4600000
0#
#4610000
1,
12
15
08
0"
b10101 1
1#
#4620000
0#
#4630000
0,
05
18
1"
b10110 1
1#
#4640000
0#
#4650000
1,
02
15
08
0"
b10111 1
1#
#4660000
0#
#4670000
0,
05
18
1"
b11000 1
1#
#4680000
0#
#4690000
1,
12
15
08
0"
b11001 1
1#
#4700000
0#
#4710000
0,
05
18
1"
b11010 1
1#
#4720000
0#
#4730000
1,
02
15
08
0"
b11011 1
1#
#4740000
0#
#4750000
0,
05
18
1"
b11100 1
1#
#4760000
0#
#4770000
1,
12
15
08
0"
b11101 1
1#
#4780000
0#
#4790000
0,
05
18
1"
b11110 1
1#
#4800000
0#
#4810000
1,
02
15
08
0"
b11111 1
1#
#4820000
0#
#4830000
0,
05
18
1"
b100000 1
1#
#4840000
0#
#4850000
1,
12
15
08
0"
b100001 1
1#
#4860000
0#
#4870000
0,
05
18
1"
b100010 1
1#
#4880000
0#
#4890000
1,
02
15
08
0"
b100011 1
1#
#4900000
0#
#4910000
0,
05
18
1"
b100100 1
1#
#4920000
0#
#4930000
1,
12
15
08
0"
b100101 1
1#
#4940000
0#
#4950000
0,
05
18
1"
b100110 1
1#
#4960000
0#
